<?xml version="1.0" encoding="utf-8"?>
<T:TicketBai xmlns:ds="http://www.w3.org/2000/09/xmldsig#" xmlns:T="urn:ticketbai:emision" xmlns:xsi="http://www.w3.org/2001/XMLSchema-instance" xsi:schemaLocation="http://www.w3.org/2001/XMLSchema ticketBai_schema.xsd">
    <Cabecera Id="_10516">
        <IDVersionTBAI>1.2</IDVersionTBAI>
    </Cabecera>
    <Sujetos Id="_10517">
        <Emisor>
            <NIF>73204334A</NIF>
            <ApellidosNombreRazonSocial>university of the witwatersrand</ApellidosNombreRazonSocial>
        </Emisor>
        <Destinatarios>
            <IDDestinatario>
                <NIF>78957653X</NIF>
                <ApellidosNombreRazonSocial>TjkoG6LEea7kdPcQ2rG1bVgjZ3qqeh0VV20We4jAX7QEtJFHC5OMZ8C3HrknIcJZ</ApellidosNombreRazonSocial>
                <CodigoPostal>oV63zk7p3B8Khig</CodigoPostal>
                <Direccion>gOcXMDREKN</Direccion>
            </IDDestinatario>
        </Destinatarios>
        <VariosDestinatarios>S</VariosDestinatarios>
        <EmitidaPorTercerosODestinatario>N</EmitidaPorTercerosODestinatario>
    </Sujetos>
    <Factura Id="_10518">
        <CabeceraFactura>
            <NumFactura>54667</NumFactura>
            <FechaExpedicionFactura>19-05-2021</FechaExpedicionFactura>
            <HoraExpedicionFactura>16:20:21</HoraExpedicionFactura>
            <SerieFactura>HDs9Yh5BSldcEcld09</SerieFactura>
            <FacturaEmitidaSustitucionSimplificada>N</FacturaEmitidaSustitucionSimplificada>
        </CabeceraFactura>
        <DatosFactura>
            <DescripcionFactura>HfoBmnnyeO6VNppZT1CpuhxoNmNvq7w7hhZLhjBzkn84Xxv6eQI2p68oUdIVMjVJrDjCg9neE3yITBJi9NlMfgAJAZhOm5r7mSxsNtt9dNwJa5B</DescripcionFactura>
            <DetallesFactura>
                <IDDetalleFactura>
                    <DescripcionDetalle>ZBEnP1NBiRQAyZX7ywcLazLMXMR9oDHbrL2jJWOghcXAy4BbqA4L7VhcHFkJUM7pOUXHn</DescripcionDetalle>
                    <Cantidad>1</Cantidad>
                    <ImporteUnitario>62.39</ImporteUnitario>
                    <ImporteTotal>75.49</ImporteTotal>
                </IDDetalleFactura>
                <IDDetalleFactura>
                    <DescripcionDetalle>q9hd0dceUPyh0Htp4rx7MsAWEESgIDc0CfR9Bgh2BdkAUHOA79XJWyKITgbdNWccSEKD25HsOo84tfS6unntklPrMln1tG3pNtcYFKgyj30wU</DescripcionDetalle>
                    <Cantidad>1</Cantidad>
                    <ImporteUnitario>42.55</ImporteUnitario>
                    <ImporteTotal>51.49</ImporteTotal>
                </IDDetalleFactura>
                <IDDetalleFactura>
                    <DescripcionDetalle>EjGJQ</DescripcionDetalle>
                    <Cantidad>1</Cantidad>
                    <ImporteUnitario>40.56</ImporteUnitario>
                    <ImporteTotal>49.08</ImporteTotal>
                </IDDetalleFactura>
                <IDDetalleFactura>
                    <DescripcionDetalle>ynapK3i6Rjee2Q4jiqpeC9BseuT8FpswuihI6jEFnPhA2JF3dIPr9QEhW7cH6O</DescripcionDetalle>
                    <Cantidad>1</Cantidad>
                    <ImporteUnitario>89.13</ImporteUnitario>
                    <ImporteTotal>107.85</ImporteTotal>
                </IDDetalleFactura>
                <IDDetalleFactura>
                    <DescripcionDetalle>vIdR338ErSB1iebVk9XXjeKLbVo1Kzb1LlNV9Rn697OVMpOyR9ii6tcjfDpHNJCgyBi7SfNqqmXIQyqzif6L9ZCo2FTFfuixfseBvx6TSt9p2iDadCldDld8MQATnc32l1f491OxhnkYLHdzUWtjA0709usB4Smc6UHCBeJ0T1qFjt3VicvIApD</DescripcionDetalle>
                    <Cantidad>2</Cantidad>
                    <ImporteUnitario>80.17</ImporteUnitario>
                    <ImporteTotal>194.01</ImporteTotal>
                </IDDetalleFactura>
                <IDDetalleFactura>
                    <DescripcionDetalle>44Z5PtGycWFPH1mkvwZcpWXPw7KUHl1iSjk5JhKltEl7xZ1woAAEBZh29OOZYQOHaMHFdxQivScVIKhrAEkrP3JQIXkJFUgdTAfxzfjbPGh51x</DescripcionDetalle>
                    <Cantidad>1</Cantidad>
                    <ImporteUnitario>18.86</ImporteUnitario>
                    <ImporteTotal>5.93</ImporteTotal>
                    <Descuento>13.96</Descuento>
                </IDDetalleFactura>
                <IDDetalleFactura>
                    <DescripcionDetalle>tGpQtDCbh40DkqBvCRdy9IObeHXYWOtGc98JpWNo21mw0peL17O0UVSp3hkCATE1UEQmCNWQoniSArRUL4Isvz7NqXUonvD6ugVFK8wLdfrdyiQMISqq00K08OKLyPoX5X4WFdlhgmXCyUbhbBKod</DescripcionDetalle>
                    <Cantidad>2</Cantidad>
                    <ImporteUnitario>99.95</ImporteUnitario>
                    <ImporteTotal>142.71</ImporteTotal>
                    <Descuento>81.96</Descuento>
                </IDDetalleFactura>
                <IDDetalleFactura>
                    <DescripcionDetalle>DBzqPQDThP0IsnjIRaRc8CelMRzfK927H00Fz2nZGeTt0Wpm16EUu6Dr6S8UHsCvdaDd4r91QBnjzfpv9Eif0w0lKntUAI4zVZzrzaqB7KsXILrZPfdG6PItjnZWIbQ9H8Qmf81cmJZqcp8oQLCficpxGsPshVDDlazLsoKtXM3V7JOBeYUS2WG1j84dIfrm</DescripcionDetalle>
                    <Cantidad>1</Cantidad>
                    <ImporteUnitario>60.22</ImporteUnitario>
                    <ImporteTotal>6.56</ImporteTotal>
                    <Descuento>54.8</Descuento>
                </IDDetalleFactura>
                <IDDetalleFactura>
                    <DescripcionDetalle>aNHlLRyhXpDpTy6DZLPbEz3V691FDG7u03UfveGx6O07ZeBKIT6FSzImCtPr1lczxgh2fvQZrZzJ0x9ZZ8YQKpdLXdOlkDz3E9MF9nBN3LMFxdH2aAkipZipzxJWyi7R5</DescripcionDetalle>
                    <Cantidad>1</Cantidad>
                    <ImporteUnitario>77.22</ImporteUnitario>
                    <ImporteTotal>80.36</ImporteTotal>
                    <Descuento>10.81</Descuento>
                </IDDetalleFactura>
                <IDDetalleFactura>
                    <DescripcionDetalle>KoqTMV4xcg3sNvRVbM9t2wRKl0ceujKs1d8KZBJb8AOqyxEEYE2E6PIsLZWrSLHWBMBydcn21NMracBiF6077ozvVmOlI</DescripcionDetalle>
                    <Cantidad>1</Cantidad>
                    <ImporteUnitario>65.64</ImporteUnitario>
                    <ImporteTotal>79.42</ImporteTotal>
                </IDDetalleFactura>
                <IDDetalleFactura>
                    <DescripcionDetalle>edXgPfULVZMfvROLD32gpoJfbITBA3J74io0bSrwETHUxJcQvRqeyUYArdd2clvZ1gSDcJCfoOwsh3v06Qc0A2jcIyViF0Z</DescripcionDetalle>
                    <Cantidad>1</Cantidad>
                    <ImporteUnitario>89.59</ImporteUnitario>
                    <ImporteTotal>93.23</ImporteTotal>
                    <Descuento>12.54</Descuento>
                </IDDetalleFactura>
                <IDDetalleFactura>
                    <DescripcionDetalle>gTuJfHy0JVtzKiXaDh61nsWeOceae9fpegi7Tv</DescripcionDetalle>
                    <Cantidad>1</Cantidad>
                    <ImporteUnitario>23.73</ImporteUnitario>
                    <ImporteTotal>0</ImporteTotal>
                    <Descuento>23.73</Descuento>
                </IDDetalleFactura>
                <IDDetalleFactura>
                    <DescripcionDetalle>EWsn6MieGYDp2W44Wuk8cwOi1Wf6XalfUC0hHqfOXoVJcaayebdRTirJZdqK32jx1Rm8WuLws8rHWERJzNFFCTySKvggKhEfUMmUbzRErw48IXkhAHnTizWsdvKI9cza9joLHbDAvbU9ZCNXxpvMuoqmahAEf8Jetdsa92DgSlgXm6KOQtfICLSsOg9wVvM6Ga4kl</DescripcionDetalle>
                    <Cantidad>2</Cantidad>
                    <ImporteUnitario>59.47</ImporteUnitario>
                    <ImporteTotal>143.92</ImporteTotal>
                </IDDetalleFactura>
                <IDDetalleFactura>
                    <DescripcionDetalle>0MP23bkvRfQYof9nCCb5mw4VLRH0EITcNbdbn7QBQw2MHHIlds5o9TkZ95iN9Fd8UCWyx3HwhRGFAPwXnW6pRZM1JVpLRWfPGjoDQCoPvtt0qybLfGh3TqBWAD4jPcWYK1MbWeWKHeV1PgSmDa8VVVUQopy2gSaRSqCJqJl8NvouziPZFqMVCVNMNbitQFueS</DescripcionDetalle>
                    <Cantidad>2</Cantidad>
                    <ImporteUnitario>29.07</ImporteUnitario>
                    <ImporteTotal>70.35</ImporteTotal>
                </IDDetalleFactura>
                <IDDetalleFactura>
                    <DescripcionDetalle>alNZ39NE8WHSFpFWF8SaDXAt2EhN9dEtjUqXMDiawgIeNxoq9uYk5eFCHEGftvytaU1l22B3968HBNyNGGdKiJoc</DescripcionDetalle>
                    <Cantidad>2</Cantidad>
                    <ImporteUnitario>97.81</ImporteUnitario>
                    <ImporteTotal>236.7</ImporteTotal>
                </IDDetalleFactura>
                <IDDetalleFactura>
                    <DescripcionDetalle>pNQwyxNggtqJ5zHvztjGrP1ZUDuNczQ78gVVYMnp32Uf0E0Szm2ZdpydN1A3Upr0Gn954NnMVjyufydBvKA0Co54f7ZM9Zky0yFmC4jZbytCGLpKSYYoZaNmBHpDN3KOBRCq1vXEDuBon4kVWRXa8skmdU0Gx4Uy</DescripcionDetalle>
                    <Cantidad>2</Cantidad>
                    <ImporteUnitario>38.46</ImporteUnitario>
                    <ImporteTotal>68.87</ImporteTotal>
                    <Descuento>20</Descuento>
                </IDDetalleFactura>
                <IDDetalleFactura>
                    <DescripcionDetalle>29ezn9GOjpuSzBRoDOUqEjBdUzoHD6TyMBmmwKloClBdmMYs3BESyXMU5JudduO9xNUD12bIJLP3MBvdoMnXUjp71GzD9mD7lwlXk2wqvhAcM2wPWsqN5rMFDflijoZevMflhBnI</DescripcionDetalle>
                    <Cantidad>2</Cantidad>
                    <ImporteUnitario>52.5</ImporteUnitario>
                    <ImporteTotal>127.05</ImporteTotal>
                </IDDetalleFactura>
                <IDDetalleFactura>
                    <DescripcionDetalle>4fwKs2Da9OBiArWfnaUZdbAjmqjwUtSP2qRM8JbhGF1cxLtrjwE613DEXM0KHiYeHLwrR68a7s1GVWf4WVdX74VFKvVcOOwJprGHJSEWSE9L8sv9H6J96hmfEEzRMbDI9ih8XUi6qbmiAWIUxvFSinsQMdPNtT9BLVEqG9DLJ0ruX04rr8w</DescripcionDetalle>
                    <Cantidad>1</Cantidad>
                    <ImporteUnitario>1.08</ImporteUnitario>
                    <ImporteTotal>1.05</ImporteTotal>
                    <Descuento>0.21</Descuento>
                </IDDetalleFactura>
                <IDDetalleFactura>
                    <DescripcionDetalle>LbdgysTdD24zgFtg9SIpNc3xMQ3VURGI79jCrD8fFRStpWdoG7b1LI1Uwko3wdTiA1j7YjyPu2pH</DescripcionDetalle>
                    <Cantidad>2</Cantidad>
                    <ImporteUnitario>22.21</ImporteUnitario>
                    <ImporteTotal>53.75</ImporteTotal>
                </IDDetalleFactura>
                <IDDetalleFactura>
                    <DescripcionDetalle>9LcFCqrmxyJJS0RbtIucnEzhoEYODJ6MFvnG8KqhrcpwvFTDhUV0WaY5tTfaDtZaJBiCt7J0EJgJK84THycyviGXIH4fzkRUh7AcEMWviPvN4c2M0pu3kWFAhrV3QuWNDXCR7v7cl6zKvXe61FUG4DZL</DescripcionDetalle>
                    <Cantidad>2</Cantidad>
                    <ImporteUnitario>72.53</ImporteUnitario>
                    <ImporteTotal>173.77</ImporteTotal>
                    <Descuento>1.45</Descuento>
                </IDDetalleFactura>
                <IDDetalleFactura>
                    <DescripcionDetalle>dO9kqe96siY3lQBWiWdfomK</DescripcionDetalle>
                    <Cantidad>1</Cantidad>
                    <ImporteUnitario>63.59</ImporteUnitario>
                    <ImporteTotal>76.94</ImporteTotal>
                </IDDetalleFactura>
                <IDDetalleFactura>
                    <DescripcionDetalle>VEgjGI40fI1Mp08sqZh3ZFLYgDKIx9w1xUXKugge19PnhffucJl7LRibhnycAyGwPGeXMFCZFeqxYtvHo1zK49fsrnyCDJpJZhHJDailkQdsLj4dY5lNqbSBX0hNRFscgm1wHXQZ15mIOTiFT33dplDEI56XgJhQmc6uutbPx1DXEGpwykVDwWEKTZEw0OL0P86qJyjntwGU2rxbpWzADX5aXzqNiFthOQIh</DescripcionDetalle>
                    <Cantidad>2</Cantidad>
                    <ImporteUnitario>92.93</ImporteUnitario>
                    <ImporteTotal>195.66</ImporteTotal>
                    <Descuento>24.16</Descuento>
                </IDDetalleFactura>
                <IDDetalleFactura>
                    <DescripcionDetalle>F5EwvrShEbu0ApahyYHpLj38te7d7tditw5eSaSGIZ02h4VoSjD9hcqk7rYGzmpWSh2C8KJwEgqlwwg3aRmmzSnqtrWlFPv8XewkXCKxixmTjwZUJEZqLGbA</DescripcionDetalle>
                    <Cantidad>2</Cantidad>
                    <ImporteUnitario>67.8</ImporteUnitario>
                    <ImporteTotal>155.87</ImporteTotal>
                    <Descuento>6.78</Descuento>
                </IDDetalleFactura>
                <IDDetalleFactura>
                    <DescripcionDetalle>C9R5uSd7jbURaiGnMbd6WkufV0HRSZYtVXtpNAo6AYWjzgE38ALWgiODqatupEQl2l1MhYgjK0y31VxpAekF5j8VJT90tZ6VBOhAabkhGbUrU8283WjYOpq0dphgPW9t3A6LJn70VCd8ZFg3C0cV4jEdzT0fGLcZigNcxgpQvC2SpyVgZRjlyEuDowv1sQ</DescripcionDetalle>
                    <Cantidad>1</Cantidad>
                    <ImporteUnitario>22.53</ImporteUnitario>
                    <ImporteTotal>27.26</ImporteTotal>
                </IDDetalleFactura>
                <IDDetalleFactura>
                    <DescripcionDetalle>VfumgRJwzRzKYNekcimCjPlfmrDhrkoEDFtb4k6JMkGTT0udxB1sAgQSzxupNHWc0awnguNxw4GiM1m80ljYiBvaoo5iJNESyiWj5Gi</DescripcionDetalle>
                    <Cantidad>1</Cantidad>
                    <ImporteUnitario>8.26</ImporteUnitario>
                    <ImporteTotal>9.99</ImporteTotal>
                </IDDetalleFactura>
                <IDDetalleFactura>
                    <DescripcionDetalle>8y2ZL8zgwx578J2l2noF6mpvjOgS4g7U8g13MuFow5W7i6U</DescripcionDetalle>
                    <Cantidad>1</Cantidad>
                    <ImporteUnitario>2.56</ImporteUnitario>
                    <ImporteTotal>2.54</ImporteTotal>
                    <Descuento>0.46</Descuento>
                </IDDetalleFactura>
                <IDDetalleFactura>
                    <DescripcionDetalle>kiSFXkRlCS5aM3oM2V5DVZKjo1D2plkgmCjxJ3wc1Cn7fhvhsCw7Mo5fgVNp2WSYPF7nBf3waBzYKF6tZ8QH9GXwbVvIKPLEGkHb2ee5WEmYIZa7bz4uY05pjwyAWPtgjGzUyBtpndq7</DescripcionDetalle>
                    <Cantidad>2</Cantidad>
                    <ImporteUnitario>5.39</ImporteUnitario>
                    <ImporteTotal>6</ImporteTotal>
                    <Descuento>5.82</Descuento>
                </IDDetalleFactura>
                <IDDetalleFactura>
                    <DescripcionDetalle>SlXZsG8G5px3zKnCWPlwesrr9tbJ1RPljhJwu3HQuZRmbWldGJo2Dlsz7thLfodWYqQG0BACjDTk8xz1ZtALVWY5cPCQPD7ExfpFJFJnMbJFAosfXlLUpQPWAvLY16PSpFJyYYcGHb6SQ6qqQl9dkgoS6pOc373CMz65qM8JAZCYaM8nidrnGPmoWtPEw</DescripcionDetalle>
                    <Cantidad>1</Cantidad>
                    <ImporteUnitario>32.52</ImporteUnitario>
                    <ImporteTotal>39.35</ImporteTotal>
                </IDDetalleFactura>
                <IDDetalleFactura>
                    <DescripcionDetalle>4Uv7OeMnvWVfKSui6BF236RxD9mof5WQW9hcbmnniLUi0i8r3orAUwPOsXD4xKFme39Cde5TraQbA0MYPNFwlP8ZZ1G0NhyYYFjcXSi1zeehMKyR5eWmoq</DescripcionDetalle>
                    <Cantidad>1</Cantidad>
                    <ImporteUnitario>44.54</ImporteUnitario>
                    <ImporteTotal>25.33</ImporteTotal>
                    <Descuento>23.61</Descuento>
                </IDDetalleFactura>
                <IDDetalleFactura>
                    <DescripcionDetalle>1PcbLYILJBQhqsrtDcwiFReVn8Tgh41uIzzv9qwSyfFlcqyhtj1Va3lKekAawWrKz3bc8BRW3w75jRreVHR5ye2NEYwrrekSDiuDC8fwFfYhnXfIXnaNhQpzSW2PYdeWc8EhAKITWDBsp0FdZtad6S1QKpWzLD93okgJu1fABEm5LEqPD0xAuEGTsfvoHN2GsMzMbLEdmkCB9II8L1LZd2tNl3ooNZFxhUET9nXoC9AwL2EHaQIOvluwI</DescripcionDetalle>
                    <Cantidad>2</Cantidad>
                    <ImporteUnitario>79.69</ImporteUnitario>
                    <ImporteTotal>192.85</ImporteTotal>
                </IDDetalleFactura>
                <IDDetalleFactura>
                    <DescripcionDetalle>ZOg7hP3m8G9qC9R</DescripcionDetalle>
                    <Cantidad>1</Cantidad>
                    <ImporteUnitario>35.39</ImporteUnitario>
                    <ImporteTotal>3.42</ImporteTotal>
                    <Descuento>32.56</Descuento>
                </IDDetalleFactura>
                <IDDetalleFactura>
                    <DescripcionDetalle>Zdes972qSJoIBxpdLd3lQixkpDviSwZe6yBSPXrdoiJffuueCVAHqwTaIcsSCObzbcwWuuWfdTMYiMwGPYkf5OY0KmaTKiM9PNPmIDceSrlTyao5997p9</DescripcionDetalle>
                    <Cantidad>2</Cantidad>
                    <ImporteUnitario>43.2</ImporteUnitario>
                    <ImporteTotal>46</ImporteTotal>
                    <Descuento>48.38</Descuento>
                </IDDetalleFactura>
                <IDDetalleFactura>
                    <DescripcionDetalle>PR9R7UR6ZS11zBVyEVPSplYWlsAUeiUuaeVrDrWg3CCqiXIFCtxU6HoSbfJbRCI4j8Ng7GRNWnzv5F7iBLBEM5t64aYjAaI6wkKJLhZFoIm</DescripcionDetalle>
                    <Cantidad>2</Cantidad>
                    <ImporteUnitario>42.84</ImporteUnitario>
                    <ImporteTotal>80.86</ImporteTotal>
                    <Descuento>18.85</Descuento>
                </IDDetalleFactura>
                <IDDetalleFactura>
                    <DescripcionDetalle>OiU3RQcJURBWcvKf</DescripcionDetalle>
                    <Cantidad>1</Cantidad>
                    <ImporteUnitario>78.11</ImporteUnitario>
                    <ImporteTotal>94.51</ImporteTotal>
                </IDDetalleFactura>
                <IDDetalleFactura>
                    <DescripcionDetalle>flvHRwMJAFSupVn0b1Wv41qEcrOW</DescripcionDetalle>
                    <Cantidad>1</Cantidad>
                    <ImporteUnitario>91.28</ImporteUnitario>
                    <ImporteTotal>87.25</ImporteTotal>
                    <Descuento>19.17</Descuento>
                </IDDetalleFactura>
                <IDDetalleFactura>
                    <DescripcionDetalle>UcwqWeHIUnK6s05WniUM5roR5oJYwrzLxbWJOJ11UAOAe5IddGbd0I82J2vG82igtolBhMP8BVFRnWHNVMBDSh36ea6aMASKZ7pm4YbNXpTBoUbCvBVf6170LcJ7ZPB5zjhHsBrTkgONTuRqN1SsKzEYoCeGh1rRr7J4WnSl7Dmfo</DescripcionDetalle>
                    <Cantidad>1</Cantidad>
                    <ImporteUnitario>83.07</ImporteUnitario>
                    <ImporteTotal>87.45</ImporteTotal>
                    <Descuento>10.8</Descuento>
                </IDDetalleFactura>
                <IDDetalleFactura>
                    <DescripcionDetalle>RiepKMLv3vwmjWJRTOGQxnyldLACb6poQ87q1q3kUz18e83bwi</DescripcionDetalle>
                    <Cantidad>2</Cantidad>
                    <ImporteUnitario>67.76</ImporteUnitario>
                    <ImporteTotal>134.47</ImporteTotal>
                    <Descuento>24.39</Descuento>
                </IDDetalleFactura>
                <IDDetalleFactura>
                    <DescripcionDetalle>hye1nojLgsS77cFLfITyoQ2DzcHwpe2y</DescripcionDetalle>
                    <Cantidad>2</Cantidad>
                    <ImporteUnitario>61.98</ImporteUnitario>
                    <ImporteTotal>91.5</ImporteTotal>
                    <Descuento>48.34</Descuento>
                </IDDetalleFactura>
                <IDDetalleFactura>
                    <DescripcionDetalle>doSoamraDSk4oVrRGc785z1DrBWWvP4uz8l4Z9jR8Sq7GalNsz7HO0ZeJwA06Z5xkTpgyZ1FybV8fljLSMiBsT9nUSqddeOjV8Ly3ILMXOxYoMLwqKWYNzpYb</DescripcionDetalle>
                    <Cantidad>2</Cantidad>
                    <ImporteUnitario>38.97</ImporteUnitario>
                    <ImporteTotal>82.99</ImporteTotal>
                    <Descuento>9.35</Descuento>
                </IDDetalleFactura>
                <IDDetalleFactura>
                    <DescripcionDetalle>PCEqfK8PjtIv3AlyAw8DLMsksvNYrZLk3qQsEVVGud3yfqOBaqEOKAB6T4EVueUX9KvJldT4hehmupqtFMgSIbwz1dzGnzQqE52g1QepwEBeNQhE4</DescripcionDetalle>
                    <Cantidad>1</Cantidad>
                    <ImporteUnitario>87.94</ImporteUnitario>
                    <ImporteTotal>106.41</ImporteTotal>
                </IDDetalleFactura>
                <IDDetalleFactura>
                    <DescripcionDetalle>hBcVFJZgODtP3ApTstpWrK1pwjSYEyHHvXPEdB3IyIB6jEnU</DescripcionDetalle>
                    <Cantidad>1</Cantidad>
                    <ImporteUnitario>26.94</ImporteUnitario>
                    <ImporteTotal>15.97</ImporteTotal>
                    <Descuento>13.74</Descuento>
                </IDDetalleFactura>
                <IDDetalleFactura>
                    <DescripcionDetalle>JJAXzLaOxKfSYjnktuLTrcWUPtk5L8kCwPGjuCA6GnUxbKwVQ1Q7tV3bFl9v4OGw3GM96P5XiEuvYptDKCdDVDGF3xL1yixppaCMBzYjYyd7DruA6FYlX4tcBC38xJ1Qq3Wuk9IMo0MRJ0U3JGbKm9PusfhS9Dr6sTsuH98D3UVwc35xkLux8yFHYxQlenqmB</DescripcionDetalle>
                    <Cantidad>1</Cantidad>
                    <ImporteUnitario>21.12</ImporteUnitario>
                    <ImporteTotal>25.56</ImporteTotal>
                </IDDetalleFactura>
                <IDDetalleFactura>
                    <DescripcionDetalle>p7XONoySDZUk6uk7OYWQiCKQf0f7F4zaibI30BF9NNQs8Aecm1JECquYGJo8skMW1aFw</DescripcionDetalle>
                    <Cantidad>2</Cantidad>
                    <ImporteUnitario>3.8</ImporteUnitario>
                    <ImporteTotal>9.2</ImporteTotal>
                </IDDetalleFactura>
                <IDDetalleFactura>
                    <DescripcionDetalle>DSFhYrcmH5tJSP92EKZGwZchmfECdggo6rvWb7329u5gB0NIlxb0aGonCLlaGyz93kMzjTyV0EBTmgHWWZg5YJQcp2dZ3vYDTRVoa8gajkgTQpxg0CpuKOgylaY749vojUbbqeJa4bZk6gMBKxFtJXrAGliSsEIn4FNIeVh3QDRPD1UeiPKl8RnoX8dZm2D</DescripcionDetalle>
                    <Cantidad>1</Cantidad>
                    <ImporteUnitario>71.54</ImporteUnitario>
                    <ImporteTotal>86.56</ImporteTotal>
                </IDDetalleFactura>
                <IDDetalleFactura>
                    <DescripcionDetalle>jFGEe1D549TEwZn2nkbWayPeCujycdBlkJ8WkKv57kNwkUmXzjhTFtz2sQfCxCJmlU4NKH1G7wlEXOXpZIpPWDD4dd1eEn7mE16JC9CmeG6Bptjnr0TkXLu7xcYP10nBm38gdmPMpRGIfG3qJcGKuvInwZBJbpo0BaZtJjn4bgcISl2j05IGPGR1Iq5Mn11NKM1FB2AYFReAF1rAsu2j2UzfoUbpTjos</DescripcionDetalle>
                    <Cantidad>1</Cantidad>
                    <ImporteUnitario>29.34</ImporteUnitario>
                    <ImporteTotal>0</ImporteTotal>
                    <Descuento>29.34</Descuento>
                </IDDetalleFactura>
                <IDDetalleFactura>
                    <DescripcionDetalle>DyEq438umPc1vUuV1Bj7YZTeNWacSxIk2hmmTiyVeJ7O5NR7J3b8nh8bgXYCK5GeFiDaTnNgq0o5gPOLmNc5hLlr5LkdYMUtjyxG0xc7Smozfre0sPZ7N1kTPXvEVF0bVzNOH3RKWPnpRwuvbs0FHTv1R5Kg5IJPL2p0wnbtt9F7GnXFp4mXPy6OwxToyHMV2T0jpH0itWfuIU5IzN6ELvJmvPgaC59eNpz0qViczCOCen18PQMlzig4D</DescripcionDetalle>
                    <Cantidad>2</Cantidad>
                    <ImporteUnitario>1.8</ImporteUnitario>
                    <ImporteTotal>0.17</ImporteTotal>
                    <Descuento>3.46</Descuento>
                </IDDetalleFactura>
                <IDDetalleFactura>
                    <DescripcionDetalle>2HiKmHQSaBjkfuZyDUoNMi6bpIQEjkBPePfKzRhhlgSMtawxf85uvNOPfRUNul1heIx0A5Qe</DescripcionDetalle>
                    <Cantidad>1</Cantidad>
                    <ImporteUnitario>20.71</ImporteUnitario>
                    <ImporteTotal>12.28</ImporteTotal>
                    <Descuento>10.56</Descuento>
                </IDDetalleFactura>
                <IDDetalleFactura>
                    <DescripcionDetalle>nS01asgwsOFkT3n2ZAT2wYdYlQAozfX2tjEwfGO74qWzNwBZ83P6Aa3r4ln5MrLUYJ0voXQGwMQtFiZWq5qkMspx95ItzeVOJqMAa</DescripcionDetalle>
                    <Cantidad>2</Cantidad>
                    <ImporteUnitario>43.99</ImporteUnitario>
                    <ImporteTotal>23.43</ImporteTotal>
                    <Descuento>68.62</Descuento>
                </IDDetalleFactura>
                <IDDetalleFactura>
                    <DescripcionDetalle>8CAzUKDZqbvUcZ79azLEqnui83qx1KFVQFmQew17JQWkXpj87PAhl42M</DescripcionDetalle>
                    <Cantidad>2</Cantidad>
                    <ImporteUnitario>89.55</ImporteUnitario>
                    <ImporteTotal>30.33</ImporteTotal>
                    <Descuento>154.03</Descuento>
                </IDDetalleFactura>
                <IDDetalleFactura>
                    <DescripcionDetalle>P23j42bXKc7TMv5G5WW0qoGlE</DescripcionDetalle>
                    <Cantidad>2</Cantidad>
                    <ImporteUnitario>90.04</ImporteUnitario>
                    <ImporteTotal>209.18</ImporteTotal>
                    <Descuento>7.2</Descuento>
                </IDDetalleFactura>
                <IDDetalleFactura>
                    <DescripcionDetalle>9lUrhEN5RAmgywNcd8NFyt8RxrJQ4s0PSVcJjrcm8ABlkrwB8aAwymZgzVvgLoKnc5GrJmq9v4KWcSzBY618UR3ViZ4Q3jO</DescripcionDetalle>
                    <Cantidad>2</Cantidad>
                    <ImporteUnitario>11.2</ImporteUnitario>
                    <ImporteTotal>27.1</ImporteTotal>
                </IDDetalleFactura>
                <IDDetalleFactura>
                    <DescripcionDetalle>xshdTNBT9yiNAW264ktGZoQQv2v0FW7iwl6wOiNEob0bIUvatWbAcxgRPaoMPJJVc20YTlAMeO4SpveSHozGhxijYN96nNH8j8k1g5uKBotYV5BIWOnYfjsLMPsFMFIJZ4j7XEybsFJZQZ0noXcaVw5ZOFQxrllXKDzgO8JCg7pTGPLkOw3bGLAHnzNIypQgDzwY8DUIEQvNIYqhfFZqILzv541DDRKwKRg0Stm</DescripcionDetalle>
                    <Cantidad>2</Cantidad>
                    <ImporteUnitario>83.61</ImporteUnitario>
                    <ImporteTotal>202.34</ImporteTotal>
                </IDDetalleFactura>
                <IDDetalleFactura>
                    <DescripcionDetalle>jXFUb1QCsNscW3vR7L8HIcgPvAzym8EPHMxGtIaMLat5nqIZ6y2N8v7TlQuuqel7X5mEvPDXKMopJ2vD7MU9aHnCr0SxcpWub4QVMR7LoVvTQvc4TFiwVRZhWbGAwsmI6Qb122Huu2Ouxfc6qCKLQ</DescripcionDetalle>
                    <Cantidad>2</Cantidad>
                    <ImporteUnitario>73.05</ImporteUnitario>
                    <ImporteTotal>7.07</ImporteTotal>
                    <Descuento>140.26</Descuento>
                </IDDetalleFactura>
                <IDDetalleFactura>
                    <DescripcionDetalle>Qex5EHa3eH6smwqbsCJzjLB9eX7YrvroofLKUhljM3Q3aWfJxj53lIOLbmYr6krqywM</DescripcionDetalle>
                    <Cantidad>1</Cantidad>
                    <ImporteUnitario>81.17</ImporteUnitario>
                    <ImporteTotal>13.75</ImporteTotal>
                    <Descuento>69.81</Descuento>
                </IDDetalleFactura>
                <IDDetalleFactura>
                    <DescripcionDetalle>qwgDCsIOk360nhyUYJnQgHghkImrXc4dbIdLaff4mVKXlvyYUkT6agNTvEw43Mqxqu6A8934uRfn0LqWYB2696gtNon6ktA4QjmzvWS9d3H3dPxRxVBNESmGqK5WicdeqgB2ZiQsXezzMTDTRML4vYQVie8Ztr2TfHUmPbmWcgWsDRv1woHVb0dhafvTKK5zR9E7KbD4UHxiAHnQe4ulzJ84LpSLBPHS4oTjZMyY</DescripcionDetalle>
                    <Cantidad>2</Cantidad>
                    <ImporteUnitario>81.29</ImporteUnitario>
                    <ImporteTotal>21.63</ImporteTotal>
                    <Descuento>144.7</Descuento>
                </IDDetalleFactura>
            </DetallesFactura>
            <ImporteTotalFactura>3992.81</ImporteTotalFactura>
            <FechaOperacion>25-06-2012</FechaOperacion>
            <RetencionSoportada>25720.36</RetencionSoportada>
            <BaseImponibleACoste>48590.23</BaseImponibleACoste>
            <Claves>
                <IDClave>
                    <ClaveRegimenIvaOpTrascendencia>08</ClaveRegimenIvaOpTrascendencia>
                </IDClave>
            </Claves>
        </DatosFactura>
        <TipoDesglose>
            <DesgloseTipoOperacion>
                <PrestacionServicios>
                    <Sujeta>
                        <Exenta>
                            <DetalleExenta>
                                <CausaExencion>E3</CausaExencion>
                                <BaseImponible>51.49</BaseImponible>
                            </DetalleExenta>
                            <DetalleExenta>
                                <CausaExencion>E2</CausaExencion>
                                <BaseImponible>5.93</BaseImponible>
                            </DetalleExenta>
                            <DetalleExenta>
                                <CausaExencion>E6</CausaExencion>
                                <BaseImponible>106.41</BaseImponible>
                            </DetalleExenta>
                            <DetalleExenta>
                                <CausaExencion>E1</CausaExencion>
                                <BaseImponible>189.92</BaseImponible>
                            </DetalleExenta>
                            <DetalleExenta>
                                <CausaExencion>E5</CausaExencion>
                                <BaseImponible>39.35</BaseImponible>
                            </DetalleExenta>
                        </Exenta>
                        <NoExenta>
                            <DetalleNoExenta>
                                <TipoNoExenta>S1</TipoNoExenta>
                                <DesgloseIVA>
                                    <DetalleIVA>
                                        <BaseImponible>1455.12</BaseImponible>
                                        <TipoImpositivo>21</TipoImpositivo>
                                        <CuotaImpuesto>305.58</CuotaImpuesto>
                                        <TipoRecargoEquivalencia>82.14</TipoRecargoEquivalencia>
                                        <CuotaRecargoEquivalencia>21441.14</CuotaRecargoEquivalencia>
                                        <OperacionEnRecargoDeEquivalenciaORegimenSimplificado>N</OperacionEnRecargoDeEquivalenciaORegimenSimplificado>
                                    </DetalleIVA>
                                </DesgloseIVA>
                            </DetalleNoExenta>
                        </NoExenta>
                    </Sujeta>
                    <NoSujeta>
                        <DetalleNoSujeta>
                            <Causa>RL</Causa>
                            <Importe>2308.95</Importe>
                        </DetalleNoSujeta>
                        <DetalleNoSujeta>
                            <Causa>OT</Causa>
                            <Importe>7647.13</Importe>
                        </DetalleNoSujeta>
                    </NoSujeta>
                </PrestacionServicios>
                <Entrega>
                    <Sujeta>
                        <Exenta>
                            <DetalleExenta>
                                <CausaExencion>E5</CausaExencion>
                                <BaseImponible>281.26</BaseImponible>
                            </DetalleExenta>
                            <DetalleExenta>
                                <CausaExencion>E2</CausaExencion>
                                <BaseImponible>163.53</BaseImponible>
                            </DetalleExenta>
                            <DetalleExenta>
                                <CausaExencion>E3</CausaExencion>
                                <BaseImponible>6.56</BaseImponible>
                            </DetalleExenta>
                            <DetalleExenta>
                                <CausaExencion>E6</CausaExencion>
                                <BaseImponible>192.85</BaseImponible>
                            </DetalleExenta>
                        </Exenta>
                        <NoExenta>
                            <DetalleNoExenta>
                                <TipoNoExenta>S1</TipoNoExenta>
                                <DesgloseIVA>
                                    <DetalleIVA>
                                        <BaseImponible>521.53</BaseImponible>
                                        <TipoImpositivo>21</TipoImpositivo>
                                        <CuotaImpuesto>109.52</CuotaImpuesto>
                                        <TipoRecargoEquivalencia>41.49</TipoRecargoEquivalencia>
                                        <OperacionEnRecargoDeEquivalenciaORegimenSimplificado>N</OperacionEnRecargoDeEquivalenciaORegimenSimplificado>
                                    </DetalleIVA>
                                </DesgloseIVA>
                            </DetalleNoExenta>
                        </NoExenta>
                    </Sujeta>
                    <NoSujeta>
                        <DetalleNoSujeta>
                            <Causa>OT</Causa>
                            <Importe>448.27</Importe>
                        </DetalleNoSujeta>
                    </NoSujeta>
                </Entrega>
            </DesgloseTipoOperacion>
        </TipoDesglose>
    </Factura>
    <HuellaTBAI Id="_10519">
        <Software>
            <LicenciaTBAI>94ni0gHrqWheKqqu</LicenciaTBAI>
            <EntidadDesarrolladora>
                <NIF>00575012N</NIF>
            </EntidadDesarrolladora>
            <Nombre>6oVALNVUGm3tspnNfEGlFjlg02GRxXPe24My0Qk3PHW0ITEo57K6b1KZD9bowm35kTbrRAJPRPaVXKlU039Z89GATarz7ryVFtIcNJQ4xL88</Nombre>
            <Version>wVMXy2Clir0sqbFoo</Version>
        </Software>
    </HuellaTBAI>
<Signature xmlns="http://www.w3.org/2000/09/xmldsig#"><SignedInfo><CanonicalizationMethod Algorithm="http://www.w3.org/2001/10/xml-exc-c14n#"/><SignatureMethod Algorithm="http://www.w3.org/2000/09/xmldsig#rsa-sha1"/><Reference URI="#_10516"><Transforms><Transform Algorithm="http://www.w3.org/2001/10/xml-exc-c14n#"/></Transforms><DigestMethod Algorithm="http://www.w3.org/2000/09/xmldsig#sha1"/><DigestValue>LdJmAmksw8esxAK2mpdXF+B782A=</DigestValue></Reference><Reference URI="#_10517"><Transforms><Transform Algorithm="http://www.w3.org/2001/10/xml-exc-c14n#"/></Transforms><DigestMethod Algorithm="http://www.w3.org/2000/09/xmldsig#sha1"/><DigestValue>xjPFSZCgBb88R1ZyJl2OfKzGUwA=</DigestValue></Reference><Reference URI="#_10518"><Transforms><Transform Algorithm="http://www.w3.org/2001/10/xml-exc-c14n#"/></Transforms><DigestMethod Algorithm="http://www.w3.org/2000/09/xmldsig#sha1"/><DigestValue>KMR6zmB9eK/xRrym3LgWdYmEChw=</DigestValue></Reference><Reference URI="#_10519"><Transforms><Transform Algorithm="http://www.w3.org/2001/10/xml-exc-c14n#"/></Transforms><DigestMethod Algorithm="http://www.w3.org/2000/09/xmldsig#sha1"/><DigestValue>gZpiwb5WS1P8WLwXkBKsWTFws98=</DigestValue></Reference></SignedInfo><SignatureValue>IO7dMzQnwZwzDhGd/ssfy0Hmreo+XND9BwWbcnPPATwuti/l1F9+o7knwrMm18+4tz2f30kvesW6iSDYFVb2eTmXhSaOWfAIhoQNXiLzFFDKumMdafjl3G/N6AbkKE+QNNyaNz4QDbhncmv2tw+oOMdSHhMmhHggHe5eP9CgU1WTUgM1vTvLLtds9uPIOKdcngXtq+4Kqe6YkgtcI4O4Ge/V/ceP5ZRA3fCxigvl/pHnB7NZZDIxp0M5dCk1aco0HrtAQRsVvWGU/gDrxuKtJ8L3yzKRIed8wHc34nvqv5+9SFgPJyt9WZuuNLkUahx13pMO8X6mEKQ2pngd4gwOIQ==</SignatureValue></Signature></T:TicketBai>