<?xml version="1.0" encoding="utf-8"?>
<T:TicketBai xmlns:ds="http://www.w3.org/2000/09/xmldsig#" xmlns:T="urn:ticketbai:emision" xmlns:xsi="http://www.w3.org/2001/XMLSchema-instance" xsi:schemaLocation="http://www.w3.org/2001/XMLSchema ticketBai_schema.xsd">
    <Cabecera Id="_9648">
        <IDVersionTBAI>1.2</IDVersionTBAI>
    </Cabecera>
    <Sujetos Id="_9649">
        <Emisor>
            <NIF>92341779E</NIF>
            <ApellidosNombreRazonSocial>bestseller</ApellidosNombreRazonSocial>
        </Emisor>
        <Destinatarios>
            <IDDestinatario>
                <IDOtro>
                    <IDType>05</IDType>
                    <ID>iCJCk5dOPA</ID>
                </IDOtro>
                <ApellidosNombreRazonSocial>wLTAJc7drlYQPKJGwrZEBvccOLc85arcuD9ZmdBYlNJCzTQrlTFAsejI98i</ApellidosNombreRazonSocial>
                <CodigoPostal>9t2tSAgg307JWN8C</CodigoPostal>
                <Direccion>FDL2mQv7AT0PQHt3gktlhUUCmwikxBQEsA0ogDRWtumGbc1ArTniRSPgTp8ZYeXajK</Direccion>
            </IDDestinatario>
        </Destinatarios>
        <VariosDestinatarios>S</VariosDestinatarios>
        <EmitidaPorTercerosODestinatario>D</EmitidaPorTercerosODestinatario>
    </Sujetos>
    <Factura Id="_9650">
        <CabeceraFactura>
            <NumFactura>32825</NumFactura>
            <FechaExpedicionFactura>19-05-2021</FechaExpedicionFactura>
            <HoraExpedicionFactura>16:19:38</HoraExpedicionFactura>
            <SerieFactura>uAM17RzQpo</SerieFactura>
            <FacturaEmitidaSustitucionSimplificada>S</FacturaEmitidaSustitucionSimplificada>
        </CabeceraFactura>
        <DatosFactura>
            <DescripcionFactura>A0W0GlQUKV14LeVG1D7H8Mu4b6yadHOaoS8SqxxuxylDbAfPIoEiv2qd7pKHt5JDxpFZ4JU3vOa8H5YHdsD3ciEwGZKLk0I3pvM9qeGSFDf</DescripcionFactura>
            <DetallesFactura>
                <IDDetalleFactura>
                    <DescripcionDetalle>HDAL7ccEJa4b4maP0uqYkhlFcDjXy1DI60Xw6mnZR9Sx39H6X4cqWwFz0jDJqm4ta3OYv7XY6ZyXN7zZzkSwR7o2ADCGaVywbJKn2E1TnTYptevCporGaFMFvsPv78P</DescripcionDetalle>
                    <Cantidad>2</Cantidad>
                    <ImporteUnitario>98.07</ImporteUnitario>
                    <ImporteTotal>151.89</ImporteTotal>
                    <Descuento>70.61</Descuento>
                </IDDetalleFactura>
                <IDDetalleFactura>
                    <DescripcionDetalle>ATifgu9Io30JRd9lVJaVllF3TAAspUMQuYHuW9WQQdBmIIWhyQ9qLbWS1VmsXBRK9DyKqcnOGGkhOlZifZffnhPuVnsbVG4pBfEyGtPI</DescripcionDetalle>
                    <Cantidad>2</Cantidad>
                    <ImporteUnitario>11.76</ImporteUnitario>
                    <ImporteTotal>26.18</ImporteTotal>
                    <Descuento>1.88</Descuento>
                </IDDetalleFactura>
                <IDDetalleFactura>
                    <DescripcionDetalle>nEl2PgkduiuDDDuuQ6B7tDnppBGUvpNuGUOSftQUlIbGpEbCSvF18dCIERiPE0GBmgUPDi6CJdaANB5fcZad3PmM4tTlLhy2wyHnAYZjj6Iaq4m5nrI3tgJtd1sr0XMiFprm7Fv6WHb9rfz17oRN9l</DescripcionDetalle>
                    <Cantidad>1</Cantidad>
                    <ImporteUnitario>62.16</ImporteUnitario>
                    <ImporteTotal>57.91</ImporteTotal>
                    <Descuento>14.3</Descuento>
                </IDDetalleFactura>
                <IDDetalleFactura>
                    <DescripcionDetalle>SIRdQxO3lXmsd97YiLP2IswfCqF3WiW6okfiW0FWee0Cp0VupmNzfcHmeeUZvY7VCFrJtGDGS2Bd88Owqkli8KcYRube3pIu26NXB9MfXDui2VsbE0XoIeqoIhi0I3f7wjxtQwDQ8KjhPCt8z73E7MFC84</DescripcionDetalle>
                    <Cantidad>1</Cantidad>
                    <ImporteUnitario>73.04</ImporteUnitario>
                    <ImporteTotal>88.38</ImporteTotal>
                </IDDetalleFactura>
                <IDDetalleFactura>
                    <DescripcionDetalle>upEhnJ3ZH3V</DescripcionDetalle>
                    <Cantidad>2</Cantidad>
                    <ImporteUnitario>11.93</ImporteUnitario>
                    <ImporteTotal>5.48</ImporteTotal>
                    <Descuento>19.33</Descuento>
                </IDDetalleFactura>
                <IDDetalleFactura>
                    <DescripcionDetalle>ysQXFnfKVBK4E73EnyA6cnD3Hzvnaq1glokyUwEPSHzcV5YQrsStdTDbcSz9aXWqSs8acYHVeuGv2bfu2ubv0tVBXgheQNQ2vQNZXp9MIQ8VkfVWWnhQcNJbY1mtcy</DescripcionDetalle>
                    <Cantidad>2</Cantidad>
                    <ImporteUnitario>45.97</ImporteUnitario>
                    <ImporteTotal>111.25</ImporteTotal>
                </IDDetalleFactura>
                <IDDetalleFactura>
                    <DescripcionDetalle>9yhPhhTP7ovnEpddEQuU33K</DescripcionDetalle>
                    <Cantidad>1</Cantidad>
                    <ImporteUnitario>66.2</ImporteUnitario>
                    <ImporteTotal>12.81</ImporteTotal>
                    <Descuento>55.61</Descuento>
                </IDDetalleFactura>
                <IDDetalleFactura>
                    <DescripcionDetalle>jfNayJX64Zaad5SVmaRVDo1VPSEWBeS2ce8GLrgIYsQcIcgUfqB7ajloUoHAMvMtJ32C2cUrxRmveIXCkWY7FhDGUX8X8DXqt7kT977329OrM6n9BWZ8JteSfo1PM0rqLBE3SBiNLAPuIl9I2etpg</DescripcionDetalle>
                    <Cantidad>1</Cantidad>
                    <ImporteUnitario>32.28</ImporteUnitario>
                    <ImporteTotal>27.73</ImporteTotal>
                    <Descuento>9.36</Descuento>
                </IDDetalleFactura>
                <IDDetalleFactura>
                    <DescripcionDetalle>L0QlSHMOkNT4tKm45X8crR4oPbwnzHwZIWbnzCm3lbREaxseptSY6uFcuRMBqG0iwRzhwPhqodch378W8J16OskL7phH3GQW</DescripcionDetalle>
                    <Cantidad>2</Cantidad>
                    <ImporteUnitario>71.13</ImporteUnitario>
                    <ImporteTotal>172.13</ImporteTotal>
                </IDDetalleFactura>
                <IDDetalleFactura>
                    <DescripcionDetalle>ecWaQHkTUB8oAxlb5sTzwRtZNbMeknqyuIVCaaTmD1Nqgquw7GjgT2hx4EQm6lx0xrKrhqJK9ebFD9xgqqMhTKD</DescripcionDetalle>
                    <Cantidad>2</Cantidad>
                    <ImporteUnitario>28.52</ImporteUnitario>
                    <ImporteTotal>43.49</ImporteTotal>
                    <Descuento>21.1</Descuento>
                </IDDetalleFactura>
                <IDDetalleFactura>
                    <DescripcionDetalle>9F2y31Q2CIHHq5vlCWVVqc8mPHIUwLMMsZ1WAy18WBNFNWw9Ek9i0w5IJOuSJyJY9CezmfLcJtt3iLRs79aYwefwkPD9iNjnyxh9IWY6KHADOW9JCPZ5aEPNXeUyn</DescripcionDetalle>
                    <Cantidad>1</Cantidad>
                    <ImporteUnitario>81.95</ImporteUnitario>
                    <ImporteTotal>11.89</ImporteTotal>
                    <Descuento>72.12</Descuento>
                </IDDetalleFactura>
                <IDDetalleFactura>
                    <DescripcionDetalle>PuK4CWZvnTT38wXRNv86XWDrf7f05orLCmR5xdUaaRKIpmvPJjyzFWxcR2zP6DKH3TMYppBjUEzxh17wTv9MGrFtOelIfq9</DescripcionDetalle>
                    <Cantidad>1</Cantidad>
                    <ImporteUnitario>4.13</ImporteUnitario>
                    <ImporteTotal>5</ImporteTotal>
                </IDDetalleFactura>
                <IDDetalleFactura>
                    <DescripcionDetalle>c4hFgunxnZcnLjtLn6uHoz3U7dlzk9DopHuhvTJohKsG7lb5Sv1mNPpW5tDjmFBBL7ewAbnusVBKRoItLM5LGx2cvqgck2w8lEf7aQOfieCjyQ2F7mNzeAm8NDCAMqQPt8sOpEwEhtFE7M1O43bG0qf8IaORoMXgREHhEe7KNQgogXVmfouoO2aR225U7Wg4d</DescripcionDetalle>
                    <Cantidad>1</Cantidad>
                    <ImporteUnitario>11.49</ImporteUnitario>
                    <ImporteTotal>13.9</ImporteTotal>
                </IDDetalleFactura>
                <IDDetalleFactura>
                    <DescripcionDetalle>IZUqSOGHonS7zTIHEfDT2Rp6O9CZVF21zoT0gMB0ytbqcXcGs7zcWfkwj57Q7qc1Tj6TjpYSu9oe2jbXqvb73yVZZeE4lMEuP8VVjnozps8MygFB5utpbq9iwimJrosWDLEKS5ASFRJzUJyjnSy1B33gK1MiNBb1lvEirQjDdn8Niuudcz0oTi5dM5ws79kDK8rg8BtPuZQsGZ4S</DescripcionDetalle>
                    <Cantidad>1</Cantidad>
                    <ImporteUnitario>42.11</ImporteUnitario>
                    <ImporteTotal>50.95</ImporteTotal>
                </IDDetalleFactura>
                <IDDetalleFactura>
                    <DescripcionDetalle>BqVvNSQlFHtvLg3X2UEMtcinHgNZ8DBvRmdKiDNxUOLzC0iIilYl17ZjC2bpj9yCnO2rd6nR6gXufUYIoRMvsXHoJ3GyZ8znxAuAyE6lBPnIoqzVZfrPazp1gtgLHOuA8X11IgCMwZytQ243o0q1djcQ4vbnLycrLxCtIqltr9CizuakXWNnxI</DescripcionDetalle>
                    <Cantidad>2</Cantidad>
                    <ImporteUnitario>5.42</ImporteUnitario>
                    <ImporteTotal>13.12</ImporteTotal>
                </IDDetalleFactura>
                <IDDetalleFactura>
                    <DescripcionDetalle>ToT3TZKSVN</DescripcionDetalle>
                    <Cantidad>2</Cantidad>
                    <ImporteUnitario>72.4</ImporteUnitario>
                    <ImporteTotal>84.1</ImporteTotal>
                    <Descuento>75.3</Descuento>
                </IDDetalleFactura>
                <IDDetalleFactura>
                    <DescripcionDetalle>E9ZXf4iIO1Ox1bDXliNFatx9tfRdEtQ64jtw6CkHduh8vvcdSP33JyvkVhEGFOemChh0eS6Y7ZcngTwpHgykBAsSN2mu30TckUEyntgrdPErCwYjL4K6MxBSZiuTMRJB713d5xVuG9YKFxdV</DescripcionDetalle>
                    <Cantidad>1</Cantidad>
                    <ImporteUnitario>24.97</ImporteUnitario>
                    <ImporteTotal>4.54</ImporteTotal>
                    <Descuento>21.22</Descuento>
                </IDDetalleFactura>
                <IDDetalleFactura>
                    <DescripcionDetalle>pLTefqS9vNm5</DescripcionDetalle>
                    <Cantidad>1</Cantidad>
                    <ImporteUnitario>72.56</ImporteUnitario>
                    <ImporteTotal>78.14</ImporteTotal>
                    <Descuento>7.98</Descuento>
                </IDDetalleFactura>
                <IDDetalleFactura>
                    <DescripcionDetalle>ZJyxZoxsLWxdVtORGsLrZyYTp7HGErrhZbDqlKSPnDNrr7CyzMaOR1BckI4tiGOn2srjgId8OAjk8oQ</DescripcionDetalle>
                    <Cantidad>1</Cantidad>
                    <ImporteUnitario>37.52</ImporteUnitario>
                    <ImporteTotal>45.4</ImporteTotal>
                </IDDetalleFactura>
                <IDDetalleFactura>
                    <DescripcionDetalle>Njwp5NwcXV8A3NgxokEz5GbVbKdi6Mb6wNk5VWYiRzWHWx260Ffg4g7bAhWxxURgQUX5tpT4Mij0smJXy5RFg1EDxoocPwWMz8wAPXpJ9F6k0UCYl2CtH9DE5tYcH2NqPseBckgu9fupzROEHtgzLwrF3lzPcqNKIMPHqS8qe3KgXLuRsmLgrhbuVm</DescripcionDetalle>
                    <Cantidad>2</Cantidad>
                    <ImporteUnitario>24.36</ImporteUnitario>
                    <ImporteTotal>58.95</ImporteTotal>
                </IDDetalleFactura>
                <IDDetalleFactura>
                    <DescripcionDetalle>2VCsglKOmyEIOmqL2UG</DescripcionDetalle>
                    <Cantidad>1</Cantidad>
                    <ImporteUnitario>16.07</ImporteUnitario>
                    <ImporteTotal>11.47</ImporteTotal>
                    <Descuento>6.59</Descuento>
                </IDDetalleFactura>
                <IDDetalleFactura>
                    <DescripcionDetalle>OCO2z85ELIwHT9oicZ83bsS8AEgAQUYwW56qqYz75O6jkaPzHk3iSo5JW70JvHt4bODLpfa7B8Z35HbKUNoOtCDHuY8</DescripcionDetalle>
                    <Cantidad>1</Cantidad>
                    <ImporteUnitario>48.22</ImporteUnitario>
                    <ImporteTotal>58.35</ImporteTotal>
                </IDDetalleFactura>
                <IDDetalleFactura>
                    <DescripcionDetalle>EzRmrBIY4TnIskK5nfqaSf2qlWLARPnqmMmtKoLpZRm3hlUk03lfVtJfbqZw5MWzXhpCB</DescripcionDetalle>
                    <Cantidad>1</Cantidad>
                    <ImporteUnitario>63.09</ImporteUnitario>
                    <ImporteTotal>2.29</ImporteTotal>
                    <Descuento>61.2</Descuento>
                </IDDetalleFactura>
                <IDDetalleFactura>
                    <DescripcionDetalle>E0iZczkvKylZAdjPcOBTMdPy1SYvOorr89D3dxpR4gCnQj8ESRHtZlfH371xpPGLAVdrKgHuHalnxDk0nxR8gxuX0G9tI7cD1fS29L03mUsXCRgLsM3ddRtlGokEtdqiOH42tdWUuIWb0KNr36jkUuGVQHWI6uNtdqT5xwBDjileT2g384hDyMt8bFnrjyr4a1fVtdErjhdIfVPXmqmTPpQIVFXHUvD</DescripcionDetalle>
                    <Cantidad>1</Cantidad>
                    <ImporteUnitario>3.38</ImporteUnitario>
                    <ImporteTotal>4.09</ImporteTotal>
                </IDDetalleFactura>
                <IDDetalleFactura>
                    <DescripcionDetalle>I2bPALZErTZ102tnlIsNDgFjzVQ2MmdIPvmoXfeKXuzQxhhD99e7xzhwcT0eTaYzafyjIwMj1YqZDJaornGX0ZXYZI5g3hlqfCfgFNUcXvyHYjxx3driQVOSglocXmCnchmayRn1omT2I48O6HBjmpuHO1XcYePobnJhMgo3bj7FElNS4TCyVBIfaiO0C5HZdOWWkO2bIRzP9JRn5qLdwRzeENWbqadO9Imrb</DescripcionDetalle>
                    <Cantidad>1</Cantidad>
                    <ImporteUnitario>93.82</ImporteUnitario>
                    <ImporteTotal>113.52</ImporteTotal>
                </IDDetalleFactura>
                <IDDetalleFactura>
                    <DescripcionDetalle>fGKBAD4VrC1gUqEsX3SXXpzhvFiuZkkAnlo8puA1b71Wjgx2vNYRmDNK8YpH6n532Y1fzIkS6UZPWxtJhcVqwUEuTfSCZxmDP1pbU0DL3Rqfd9tnw9gEddznHPz</DescripcionDetalle>
                    <Cantidad>1</Cantidad>
                    <ImporteUnitario>73.52</ImporteUnitario>
                    <ImporteTotal>88.96</ImporteTotal>
                </IDDetalleFactura>
                <IDDetalleFactura>
                    <DescripcionDetalle>dfiBsQsvqyFQqKMbJQADkedipBayzA7l1JANcKxL5IzLKeI7L3lvaLwlTjfwjXHG64Lagh24TOYWeIfGPyeC9n9savc</DescripcionDetalle>
                    <Cantidad>2</Cantidad>
                    <ImporteUnitario>76.79</ImporteUnitario>
                    <ImporteTotal>59.47</ImporteTotal>
                    <Descuento>104.43</Descuento>
                </IDDetalleFactura>
                <IDDetalleFactura>
                    <DescripcionDetalle>it5kdThuRMkIBnl0BuiLfRgBMpXo9BdH3u5e7rLmdqOQZD91MuCIigpHavgz5X7R8DuSMq0vgKOPsjjKLKpsUiLRNZgr2xPTrL5fiBifgpII3k4KPs3fEIDvBSk1DpGqYP2XF5dLAn4NykjMX1i0gWN</DescripcionDetalle>
                    <Cantidad>2</Cantidad>
                    <ImporteUnitario>10.38</ImporteUnitario>
                    <ImporteTotal>15.57</ImporteTotal>
                    <Descuento>7.89</Descuento>
                </IDDetalleFactura>
                <IDDetalleFactura>
                    <DescripcionDetalle>g58O9OnXdLavtTYvv3klPSOPz9dpoWBE25BMLCenYo17bSacDtgfCER7xWAeT6Oa7PzSCvsXZ4YyYZNA5fXQr01m9e0mNOJ9iFpEhjcQArsGb21FEVbvbkytbictSDWrJ79F7MevSt6hHksJjaQwD2X63sdHwaLJhSd1XgaChnFC7iN</DescripcionDetalle>
                    <Cantidad>1</Cantidad>
                    <ImporteUnitario>26.96</ImporteUnitario>
                    <ImporteTotal>23.49</ImporteTotal>
                    <Descuento>7.55</Descuento>
                </IDDetalleFactura>
                <IDDetalleFactura>
                    <DescripcionDetalle>uXSaDFZeDYO5D7FYWMUWowrwa</DescripcionDetalle>
                    <Cantidad>1</Cantidad>
                    <ImporteUnitario>48.38</ImporteUnitario>
                    <ImporteTotal>49.76</ImporteTotal>
                    <Descuento>7.26</Descuento>
                </IDDetalleFactura>
                <IDDetalleFactura>
                    <DescripcionDetalle>jcmQ6pgV0atpHLgz36bjORCeQQr5tjyQXQpntB8J6B4LmiSwBpBZ5l5bqXklcmgxQ2fhki0wASx3w9m3U1XGg2</DescripcionDetalle>
                    <Cantidad>2</Cantidad>
                    <ImporteUnitario>67.61</ImporteUnitario>
                    <ImporteTotal>142.34</ImporteTotal>
                    <Descuento>17.58</Descuento>
                </IDDetalleFactura>
                <IDDetalleFactura>
                    <DescripcionDetalle>6seEHlnojVMyUhs1PP4JeqXJXqsX0ucV2Gl7VlTk6i5gCvYJ9oZA4JV6guQkei04zyEKf5BIQ0dDv9zCI5Jnoawko3XzcP2kf9nvifZiw1i2wsU1ZS9F9TKuCN0UZUkhh7tXcRyoVsk6XQKBdY3bmgwevQHfeA3SLfw3qGzA9236gvOMNKM6onKpXurSc4U</DescripcionDetalle>
                    <Cantidad>1</Cantidad>
                    <ImporteUnitario>73.74</ImporteUnitario>
                    <ImporteTotal>41.04</ImporteTotal>
                    <Descuento>39.82</Descuento>
                </IDDetalleFactura>
                <IDDetalleFactura>
                    <DescripcionDetalle>Nt4H51BE766DLlwQw8jjUuzhT9NF1jQB9JLuAOnzuf46PkIwVzQkMKxXL8gRk7qJ8gTlY436wrvdMY8BcDeSMcZh6ZHwxrXxNOCpprdnj7PJWA9yzagmZmmdoCr9c8oMQkz6SmrXVJSRmbsaIA1Lq20MBdzIDT5JlLGdz5K5N</DescripcionDetalle>
                    <Cantidad>2</Cantidad>
                    <ImporteUnitario>85.58</ImporteUnitario>
                    <ImporteTotal>103.55</ImporteTotal>
                    <Descuento>85.58</Descuento>
                </IDDetalleFactura>
                <IDDetalleFactura>
                    <DescripcionDetalle>bBoKbDUpthXKN22pP31nJrCXUQRlQbt2oSYe3mpMFzmEihmLL25JgTnkAKh9frDTdXG8pmL5XjCCL5nzNjmGVLIVI10JesWngJLzad8TiBiZimHWYAoxrTI9OcYfKnzM8fwU2fuJygpD3J01hmYMw</DescripcionDetalle>
                    <Cantidad>2</Cantidad>
                    <ImporteUnitario>10.82</ImporteUnitario>
                    <ImporteTotal>20.95</ImporteTotal>
                    <Descuento>4.33</Descuento>
                </IDDetalleFactura>
                <IDDetalleFactura>
                    <DescripcionDetalle>xa3130BgcAu9u2r3lMqr1ZRJ4TeNC5dvDRRPnoNkQi8c5iyQgWTjHXErFXE1L1d5kLdrfNK7sXBsF4kQ9uh3PD6VNJ1VOYx3dtoGWi7gRi5rcxl8T7ljKyWZt2qlFjOQ1XevpPwY0BO0pQiTknrCb</DescripcionDetalle>
                    <Cantidad>2</Cantidad>
                    <ImporteUnitario>88.49</ImporteUnitario>
                    <ImporteTotal>201.3</ImporteTotal>
                    <Descuento>10.62</Descuento>
                </IDDetalleFactura>
                <IDDetalleFactura>
                    <DescripcionDetalle>L2252sERi5C6eAfoBN1VWh6W1NQeeZIQJV64h6TshGpFBFKc2jct3ZPfTEFZ1o3h7ExOxqBGyvtKh7AAig0M9sxdijTB6YhWdextVB1K2INSRnD51P5iVyIBwgLkElYKnIhTnVnnOSAwpW50rIXLhj0fk</DescripcionDetalle>
                    <Cantidad>2</Cantidad>
                    <ImporteUnitario>75.85</ImporteUnitario>
                    <ImporteTotal>183.56</ImporteTotal>
                </IDDetalleFactura>
                <IDDetalleFactura>
                    <DescripcionDetalle>80JPwtXkXTc0yd1ZCiiZLbXxduDVFcI48DLdDCft6lexii67j5TIjID9cpEXk8Y9hb9VEsRw7XMI4Lv1ayAgxxQK0dYPLDo5EHmUyieFjUYIsyVdT5n399tCEgQSczfVCagozRf04VcagIzHhTflb5dT3VKSgLslBJtVPRuzNpGQl3Q</DescripcionDetalle>
                    <Cantidad>1</Cantidad>
                    <ImporteUnitario>13.82</ImporteUnitario>
                    <ImporteTotal>0</ImporteTotal>
                    <Descuento>13.82</Descuento>
                </IDDetalleFactura>
                <IDDetalleFactura>
                    <DescripcionDetalle>KvBttgNuaSOg6xLUWJsBFdQWNmmMW6NNGf2ZN5IWSkTUKQqAviLPnqDr3z268eCQAsPYs7voeoJpXOxLY2o2N93FzIdKCELHyqNnjhtrc</DescripcionDetalle>
                    <Cantidad>1</Cantidad>
                    <ImporteUnitario>48.25</ImporteUnitario>
                    <ImporteTotal>45.53</ImporteTotal>
                    <Descuento>10.62</Descuento>
                </IDDetalleFactura>
                <IDDetalleFactura>
                    <DescripcionDetalle>uSA4ia2fLg1Pl2HPvIQF5M4x3XBPfJjkJbCoIHHx2t0eJ7gI4JvCGPRqaREw1jCfbipBaoRCzHs1FIEWUQzkPexX6nZDENng7PDTHHzjgRHmxIKDL0aT7moE2zmf6bFn1zCLBjRG0cCCEgbm1fMHm8Z09</DescripcionDetalle>
                    <Cantidad>2</Cantidad>
                    <ImporteUnitario>27.79</ImporteUnitario>
                    <ImporteTotal>47.08</ImporteTotal>
                    <Descuento>16.67</Descuento>
                </IDDetalleFactura>
                <IDDetalleFactura>
                    <DescripcionDetalle>iYxnGLDjiitcHOhiIpbQyFP2t83K1SnDHUeYGWrWDUXLNFMAeMIMo</DescripcionDetalle>
                    <Cantidad>2</Cantidad>
                    <ImporteUnitario>45.66</ImporteUnitario>
                    <ImporteTotal>110.5</ImporteTotal>
                </IDDetalleFactura>
                <IDDetalleFactura>
                    <DescripcionDetalle>9sTrWxmrpUV1PGDoqRLYsmWSnpKpvi3G2ShhoXOWxjjVYHjSkI2oSh3TmItzurv1GKf6x77m6tADoA99r65dobvN5CX3WciXbnBdOKEnW43UZE</DescripcionDetalle>
                    <Cantidad>2</Cantidad>
                    <ImporteUnitario>98.93</ImporteUnitario>
                    <ImporteTotal>67.03</ImporteTotal>
                    <Descuento>142.46</Descuento>
                </IDDetalleFactura>
                <IDDetalleFactura>
                    <DescripcionDetalle>7w5al3cdTGQn0S6uuTRKHxjMHHubx3oZGPfv3BXuxaX5IUWJuDfqGCq3ZMhzT3jWqgy9p</DescripcionDetalle>
                    <Cantidad>2</Cantidad>
                    <ImporteUnitario>83.93</ImporteUnitario>
                    <ImporteTotal>123.89</ImporteTotal>
                    <Descuento>65.47</Descuento>
                </IDDetalleFactura>
                <IDDetalleFactura>
                    <DescripcionDetalle>Z2UNebGU8aElQbqQKgRPiuEEmGWmEeZlqdxIQ9jNU5kbjb3O4wfDACSyVMY481g2Kt6xLPSzmeZhh7VOJvRQaGnJenUybEqcipBFmanqeFER8YLpsYgw2NAUKYYb</DescripcionDetalle>
                    <Cantidad>2</Cantidad>
                    <ImporteUnitario>29.19</ImporteUnitario>
                    <ImporteTotal>70.64</ImporteTotal>
                </IDDetalleFactura>
                <IDDetalleFactura>
                    <DescripcionDetalle>6426jyYPvu9ymI4CUKLU8fvOTTe9YtsL1vuBLNkk4tPauY20Ex7JxnBoiLb34C9Fx2bPAfY5qpXIoB9ceOiIBI1mtOFRkguR2cqa2u0eG0pRgci6X7fYfFeehTfU4Bc6RNz4c4TrRRoTFR6DYD6AilorZqxUgRQJ1Rl5hfg2YYjBbBLFQIfjRms29b5MBkOUcfmYujrJpok7BfWmMJxX7tsEFDSONM82NSHUEhRZyPiRUIh</DescripcionDetalle>
                    <Cantidad>1</Cantidad>
                    <ImporteUnitario>25.03</ImporteUnitario>
                    <ImporteTotal>30.29</ImporteTotal>
                </IDDetalleFactura>
                <IDDetalleFactura>
                    <DescripcionDetalle>1uOiL81YUI6GzWyroRITKbXqgDErzopRjFFqGdcGGe8X4piescxWPGcYQf0uoSk1yIropHgsLoJzybWWK8Wk4XLZr2cP5ML9xzg1UJSsNTHR9Q5bEg6KIvhvloSHbyGKMaqoMV0NVSiE</DescripcionDetalle>
                    <Cantidad>1</Cantidad>
                    <ImporteUnitario>95.26</ImporteUnitario>
                    <ImporteTotal>115.26</ImporteTotal>
                </IDDetalleFactura>
                <IDDetalleFactura>
                    <DescripcionDetalle>KZPyoxyqzOHJlPPejOgDLcQ60arLbNTaOlQzN9NG4uomGfoMNv0F9NbwChimePYZC5UTB88wSym3H3NCvUWK1SM0Fn1D3PeDx0SskNZgCIWQVBuOizcLcQQ1PfjYEJZHrEzGolI7eZn9RnaJhLgP7tOsxdhyEy3PJ8a7tCaLfTFOeDCvFxLWucws4U9YfetpFVxRpYuTR3azOF1rwba5LQhsn5kJu0M</DescripcionDetalle>
                    <Cantidad>2</Cantidad>
                    <ImporteUnitario>93.61</ImporteUnitario>
                    <ImporteTotal>226.54</ImporteTotal>
                </IDDetalleFactura>
                <IDDetalleFactura>
                    <DescripcionDetalle>QoSDZkojOGUZTRVkdgoDfsRSfYI0O625OjbMtORWA0uTuKz2ohsz2C9khDfUJTN4nYOd3L6gn2VzyCO6sMEK6gK8dIDGM63Igg0Rt0K2h7Fiv58wOrruKNzzTSPlTUuIb2vNmzWZa</DescripcionDetalle>
                    <Cantidad>1</Cantidad>
                    <ImporteUnitario>36.09</ImporteUnitario>
                    <ImporteTotal>13.1</ImporteTotal>
                    <Descuento>25.26</Descuento>
                </IDDetalleFactura>
                <IDDetalleFactura>
                    <DescripcionDetalle>tWCZGdIJA8opQx46Xrop0N9mBv42LAzJzJrD1AaGMcRrXZ72AD9bYOoYNtqVQZMAvHt9rMxInbIxRzObKA2ntLf1szszObG6LY0x35u0kzp3MFXFBKNEc4PEhFtrCFjl2SrIHc2V9SWYHn43PM5lj8C4jxhLyLLCuEBT5Ug57L6nMAXlmjKGoX6jDcfApFzzZi5TcJUiQ2OaabBMiQhNIaZFyJ1ZTOwnfUnlzKh7txqOjaw</DescripcionDetalle>
                    <Cantidad>2</Cantidad>
                    <ImporteUnitario>26.43</ImporteUnitario>
                    <ImporteTotal>63.96</ImporteTotal>
                </IDDetalleFactura>
                <IDDetalleFactura>
                    <DescripcionDetalle>FhJPrI4cyvlZAgHFMttVnbwxTME2OL0atzpkIx48m5WW8QECtvHPB0YinPA5hbE7ldC8YectFqw77B14IGMJLd1rYaSldOyF7CH3CQiERQucac9RbpZfBn95GuWjKUYQoylITxFONB8XYCmT6LLEHA5dXu7DRuKKZXA2t9XKIMXYwl57xaePKMcNGOjTbmwk30RqcCVGcjzZPlrkFJUf</DescripcionDetalle>
                    <Cantidad>2</Cantidad>
                    <ImporteUnitario>83.87</ImporteUnitario>
                    <ImporteTotal>202.97</ImporteTotal>
                </IDDetalleFactura>
                <IDDetalleFactura>
                    <DescripcionDetalle>hmC64ShSu3Mh56HcUiQOCaGxsenHRbl2qkw71uqHzMLvdtMhXSODMGyKKuSuA3b6ndsrsMTmQ9MOPOKm6ebrGlaQn64Qapgxm</DescripcionDetalle>
                    <Cantidad>1</Cantidad>
                    <ImporteUnitario>53.9</ImporteUnitario>
                    <ImporteTotal>60</ImporteTotal>
                    <Descuento>4.31</Descuento>
                </IDDetalleFactura>
                <IDDetalleFactura>
                    <DescripcionDetalle>DKCvw9w2IE4m6CDSUtP6vwT8szDAH1oSS8rewFOhDHu0PHfqHvCXPQPrDvv9kAgwCDhsO1gRsEfmBdQW0Kfopcjjgh924BeeBnKjiUmngMhFqG42MFCSxa2VElIsm13H0wtMUoaH7BHR4qGQAch8Asdng</DescripcionDetalle>
                    <Cantidad>2</Cantidad>
                    <ImporteUnitario>89.24</ImporteUnitario>
                    <ImporteTotal>215.96</ImporteTotal>
                </IDDetalleFactura>
                <IDDetalleFactura>
                    <DescripcionDetalle>xFGd2WRQEL4HZ88g2KVr90GSqyERDwsRkx5kYapWMJBw7BZifG</DescripcionDetalle>
                    <Cantidad>1</Cantidad>
                    <ImporteUnitario>41.2</ImporteUnitario>
                    <ImporteTotal>5.98</ImporteTotal>
                    <Descuento>36.26</Descuento>
                </IDDetalleFactura>
                <IDDetalleFactura>
                    <DescripcionDetalle>X9k9aT6WaFWayV4LZQifOf2i8u7WVhOJo36VAAACMLOnYQHeaijyMvyWMY7Yr9CSlp1KcPyTvCNlkrgIsBKj190TYTJtkNxZ4JKwq1QmE4jaEeZX9nrHDmw1KyMtHl35pMEopnxYoHOsA2I5Ij19cdU4M4IqxbCD</DescripcionDetalle>
                    <Cantidad>1</Cantidad>
                    <ImporteUnitario>33.79</ImporteUnitario>
                    <ImporteTotal>37.21</ImporteTotal>
                    <Descuento>3.04</Descuento>
                </IDDetalleFactura>
                <IDDetalleFactura>
                    <DescripcionDetalle>Ji9olnnXpcRWtFCdXbyenwUk8UPCpgDM4HVrj9OFN</DescripcionDetalle>
                    <Cantidad>2</Cantidad>
                    <ImporteUnitario>36.63</ImporteUnitario>
                    <ImporteTotal>58.5</ImporteTotal>
                    <Descuento>24.91</Descuento>
                </IDDetalleFactura>
                <IDDetalleFactura>
                    <DescripcionDetalle>t2P6NUKLl0u0MQwVSpnSJIISDRXtj9wB0acVKWFsfAMmaOjiKSzbCtxLwleMswMVgdB39ODnvs0GrT9QU3UaJyOvVyGVIrYsgUDTeOg97JSf14utscq6PJEF9Nk8HKFnf8OuTe3DNAdczFfghK</DescripcionDetalle>
                    <Cantidad>1</Cantidad>
                    <ImporteUnitario>89.97</ImporteUnitario>
                    <ImporteTotal>108.86</ImporteTotal>
                </IDDetalleFactura>
                <IDDetalleFactura>
                    <DescripcionDetalle>Uvx1mkilZ4jDtSDq6RNfFCSAsPKO5yx7MOfxcztSUrn8E4P64VbT1OnKC4KjipVNhVJNYdUd33LYm1CN1IhRgrGdr1vJoMS0HBtGvWU8zAcfi2d8wTO4d1w7hBD0u05XwtxJQ1Aq8Ju6VKxaiGIEkRp160hU2i4HAWWbG66W9LDHN0z7</DescripcionDetalle>
                    <Cantidad>1</Cantidad>
                    <ImporteUnitario>6.45</ImporteUnitario>
                    <ImporteTotal>7.8</ImporteTotal>
                </IDDetalleFactura>
                <IDDetalleFactura>
                    <DescripcionDetalle>jALyC9bgSlwhVrvP5Q3xGhAjSC9bJSc97sTZ4DPpjLozUVOzuZOA5iV7uIfyCXcHWKkJX1Th4Nksj9zPvoyX8YEGHBDm64sGKtVrN5OanVIU0z</DescripcionDetalle>
                    <Cantidad>1</Cantidad>
                    <ImporteUnitario>27.21</ImporteUnitario>
                    <ImporteTotal>10.87</ImporteTotal>
                    <Descuento>18.23</Descuento>
                </IDDetalleFactura>
                <IDDetalleFactura>
                    <DescripcionDetalle>JiMCfkqRSO0qCHpWuDbyB5JdUP7C5zZlgLC1wMJnJ0EWnWCSvfKhJ9lEtS4AUnQngP2OezvOmbwVHkYIo2NmTUUsrRQ3TYw3YAhh0k4Cd3cr9tgFRPLcZ0BI8seyvNMp5zbTkTDthsHAxBxUHxp7puIxApU7wTzsGzMrCSaPRFS6bWmp55Kt1sgI0MDgCElMxrPZNm6KDmZ9cvRBKZY4y1SY75DkDqVDkV</DescripcionDetalle>
                    <Cantidad>2</Cantidad>
                    <ImporteUnitario>67.97</ImporteUnitario>
                    <ImporteTotal>164.49</ImporteTotal>
                </IDDetalleFactura>
                <IDDetalleFactura>
                    <DescripcionDetalle>z0si7P4AupnlpFbRKCwJfUY7LCakQh5Btwd4S2PUci8Mo2v72Y</DescripcionDetalle>
                    <Cantidad>2</Cantidad>
                    <ImporteUnitario>23.85</ImporteUnitario>
                    <ImporteTotal>2.89</ImporteTotal>
                    <Descuento>45.31</Descuento>
                </IDDetalleFactura>
                <IDDetalleFactura>
                    <DescripcionDetalle>D5LMnqTJucsocE5ZqqrEMk9O7TUE3E6XNGV3IX9Vgo8mEfZkSU7yTlWQJ0kGBr</DescripcionDetalle>
                    <Cantidad>1</Cantidad>
                    <ImporteUnitario>32.61</ImporteUnitario>
                    <ImporteTotal>39.46</ImporteTotal>
                </IDDetalleFactura>
                <IDDetalleFactura>
                    <DescripcionDetalle>94IkvkzRik0a0ubnw</DescripcionDetalle>
                    <Cantidad>1</Cantidad>
                    <ImporteUnitario>16.97</ImporteUnitario>
                    <ImporteTotal>13.14</ImporteTotal>
                    <Descuento>6.11</Descuento>
                </IDDetalleFactura>
                <IDDetalleFactura>
                    <DescripcionDetalle>RuPaO0dITNqqvpvLoMy3DZDqRlu0ACYuOteDL2fxB8Wop0yKcxfb47HcyfKpjpZ28fRatmm87jn4d51sgF17JplG2QJYAjMXPIh1a6yePY5WNrhWeRUafBDTVgXhf7yqMO9eN8DzaDJpUxXD73Ybmr18mupy7hK9wtjtCHX1WpPEJogC6EWT5mWaL0SCRDsvz83a2YWFkOCy6EwO6fCRedejPsqfQINTJOyXH2GwHqSOWYri</DescripcionDetalle>
                    <Cantidad>2</Cantidad>
                    <ImporteUnitario>16.49</ImporteUnitario>
                    <ImporteTotal>39.91</ImporteTotal>
                </IDDetalleFactura>
                <IDDetalleFactura>
                    <DescripcionDetalle>w8lFiUvZAW4E2uyVfnEv0lfrf5e</DescripcionDetalle>
                    <Cantidad>1</Cantidad>
                    <ImporteUnitario>79.8</ImporteUnitario>
                    <ImporteTotal>49.25</ImporteTotal>
                    <Descuento>39.1</Descuento>
                </IDDetalleFactura>
                <IDDetalleFactura>
                    <DescripcionDetalle>thgCTgafOTw1UfxDenosbtzlffUwlLivWZrfI5R6HMMIHN47THLLR4zyAqwaIDTWVCoZwvE2kpCIfBDJy1hUA7ZmrsUAbUjAhEjfH9bM6361iamcfa1do0fb7dViNxTCLkXOETl5742ms8avAGBbpvU98tPURyy1CxH4lumzX1M2Ci76OG3XWiIakeUN633HwLrpbz7HcdfQJzbRDBwf4PFpd9K9NKLuxd9wl6a0tqucYHNSTeigTnyV</DescripcionDetalle>
                    <Cantidad>2</Cantidad>
                    <ImporteUnitario>18.23</ImporteUnitario>
                    <ImporteTotal>44.12</ImporteTotal>
                </IDDetalleFactura>
                <IDDetalleFactura>
                    <DescripcionDetalle>UZXT1etyVqA6W9U5ENRqrIartSgQOt5YmKb3xXlDtowDJqr91jIt6hmZ9yAi59qtxpcBJywFeUWGFKVI7lsw2HXzIJfWLyZ1DFh0zK6jW3Wop0Lb6vf8Yns9i0EE1NgrbHGjnShQYmk0iUPQpXfB7NoH1mkqZUGv3b1bsse2R48KfTE8TURoF0RAD3CLpzP3gFnkavaIQSBtgFBY307cbS2uZ4tf0XxDrY3</DescripcionDetalle>
                    <Cantidad>1</Cantidad>
                    <ImporteUnitario>90.62</ImporteUnitario>
                    <ImporteTotal>109.65</ImporteTotal>
                </IDDetalleFactura>
                <IDDetalleFactura>
                    <DescripcionDetalle>MV5GnHECbaVE1dp5Pw2o107WBSGmYT4Lrzq9PW5Y11lqhszkK0XIxyFJnOsUdkBmnMe36Db1Gc6yc1grZGJnJq3LR0KvwiBy4GsiT7DlNt4Yh8x6rf7eo8Q8xHbqeI11GrTRFHtK5PVwPcs55yyA2HMRfDCFeIRkwBBeHL66Tgn6A3VOB</DescripcionDetalle>
                    <Cantidad>1</Cantidad>
                    <ImporteUnitario>98.95</ImporteUnitario>
                    <ImporteTotal>119.73</ImporteTotal>
                </IDDetalleFactura>
                <IDDetalleFactura>
                    <DescripcionDetalle>44LlfcbL7wItM8ejCK1W1SErPICUBO3NVkjsbtOv186StX7X78iVYwoKA8yMq3I5r48b1nYGieV3qzrKgTKvhH5ZQ6Zee9SWPBskG8SB4y4SlY1LEcLNgvjp1NNolnhyPwVBie87IQyhIwbTFsorhK4Y6p7FaXLSkuXPSsHVldbS3u4lCQhDpjjuhhxdFZ40ymWRiZ2oPhY8HV43j5QrNYUmOdCqAMfHkh7CdAap3GBkEX8YS</DescripcionDetalle>
                    <Cantidad>2</Cantidad>
                    <ImporteUnitario>57.42</ImporteUnitario>
                    <ImporteTotal>138.96</ImporteTotal>
                </IDDetalleFactura>
                <IDDetalleFactura>
                    <DescripcionDetalle>27dDjhcwgaEVwpDDBqYcCQyoN7qYtdEIdgcatQtMLaQlKTOcfu</DescripcionDetalle>
                    <Cantidad>1</Cantidad>
                    <ImporteUnitario>8.06</ImporteUnitario>
                    <ImporteTotal>9.75</ImporteTotal>
                </IDDetalleFactura>
                <IDDetalleFactura>
                    <DescripcionDetalle>7vsYgAuAJXBMqwEbWgMjxWsYepE22OWQ6vDUzFuxKra54zXMqZ7pVOxYwPaYcuQBqv0K5MJ7XorogotKwNlRdoUPLArOF8RdSUwTt5HeOQJijpJxy3liv3i89q2Mi0DCQv97sm9LM4VYPAtolGIplCoQDb8uCBgHY1ujYOG</DescripcionDetalle>
                    <Cantidad>2</Cantidad>
                    <ImporteUnitario>78.74</ImporteUnitario>
                    <ImporteTotal>190.55</ImporteTotal>
                </IDDetalleFactura>
                <IDDetalleFactura>
                    <DescripcionDetalle>Uuoza3fwPzookcWc8o8d7uRMxT5rEThjblOpgce2VNBq0q9myGexGaF3Qk0HqOa0b3mA8HOQa9yhXr9xVEtc5MNyblYz10vU6Mt1pgTlRmecDgF1j0TvjC7t6LJ6dC7yF6dBAXxkVhOrkASEXSVHrnFQkAoOIcg5TkvClzIM2XcgnXS4</DescripcionDetalle>
                    <Cantidad>2</Cantidad>
                    <ImporteUnitario>94.59</ImporteUnitario>
                    <ImporteTotal>194.57</ImporteTotal>
                    <Descuento>28.38</Descuento>
                </IDDetalleFactura>
                <IDDetalleFactura>
                    <DescripcionDetalle>VJsjbkXhh7z21Xk7kj4jSwtqQv2mrNmds81Y925y0CKduvUf1uv1MAhpjA1jKLRFRpWjfboYPxgto9GkQMoN328z4ofRSiLqZN8bYWqy4NqhmTCM8hqJEa9eG1WzU9XyjRTKPC8z</DescripcionDetalle>
                    <Cantidad>1</Cantidad>
                    <ImporteUnitario>49.44</ImporteUnitario>
                    <ImporteTotal>59.82</ImporteTotal>
                </IDDetalleFactura>
                <IDDetalleFactura>
                    <DescripcionDetalle>fZzz7Ya9oTdRQ9PUfA3fYVRM8syZ7Gh8DOhBLQ7hhIuUY8EIgDpBnLiXZN1U5LI9rFLqre9HnaCAQJFLz2xzW6pm8Q</DescripcionDetalle>
                    <Cantidad>2</Cantidad>
                    <ImporteUnitario>70.83</ImporteUnitario>
                    <ImporteTotal>22.29</ImporteTotal>
                    <Descuento>123.24</Descuento>
                </IDDetalleFactura>
                <IDDetalleFactura>
                    <DescripcionDetalle>oZ0SiYyQlZJ9Tr4tzq18vKDRTE4yv6b10WacS10CbNz7c5N009vHDAjDzu5uwyhBWKa513V6dPhhcOtwdRtRFxHXu908pvMOvtomYk8MMPLc0jQs7AK</DescripcionDetalle>
                    <Cantidad>2</Cantidad>
                    <ImporteUnitario>86.05</ImporteUnitario>
                    <ImporteTotal>162.43</ImporteTotal>
                    <Descuento>37.86</Descuento>
                </IDDetalleFactura>
                <IDDetalleFactura>
                    <DescripcionDetalle>RrCTpqMlxDmnJcrso8MdiuKgaQUEJU5YUvOsuIIpk0akRGklcR1398A3bYZsBUCu</DescripcionDetalle>
                    <Cantidad>1</Cantidad>
                    <ImporteUnitario>25.53</ImporteUnitario>
                    <ImporteTotal>30.89</ImporteTotal>
                </IDDetalleFactura>
                <IDDetalleFactura>
                    <DescripcionDetalle>0BK6ViLTaFNs5tL0BpyvNekvgjEfIXgWT3qilW36BTlsnUjyJ6entMqdCo0igyGKDqfwvP1WgxlhDmfgYZkbTJCHygPGjrlbcmFWA3I07gUGP1tyhJAzbdUJ0Q1</DescripcionDetalle>
                    <Cantidad>1</Cantidad>
                    <ImporteUnitario>33.05</ImporteUnitario>
                    <ImporteTotal>39.99</ImporteTotal>
                </IDDetalleFactura>
                <IDDetalleFactura>
                    <DescripcionDetalle>CKkw2bKozFOoosr81lkbSunRFTdPn33692Fget3IG9WClrpYPFOENHg2Fv5d7iwmh4xBIgU7sGKfAdD9R</DescripcionDetalle>
                    <Cantidad>1</Cantidad>
                    <ImporteUnitario>50.15</ImporteUnitario>
                    <ImporteTotal>13.95</ImporteTotal>
                    <Descuento>38.62</Descuento>
                </IDDetalleFactura>
                <IDDetalleFactura>
                    <DescripcionDetalle>7ODNrovo2T8RgIjtV</DescripcionDetalle>
                    <Cantidad>2</Cantidad>
                    <ImporteUnitario>36.68</ImporteUnitario>
                    <ImporteTotal>88.77</ImporteTotal>
                </IDDetalleFactura>
                <IDDetalleFactura>
                    <DescripcionDetalle>M01IjmwFCITJcsbKEg8KvSbIzi2GhbMC4awpZRUHLkMZJ9VQQqPK7xd2OpfpJyihjUZBCjqi50CdbqIqM2jzbVA4HMDSSu8YNZSt3EP8ODuBXp6rZUWHNSpPHYnySVAdjJ6Uoy4ReVnj0Vdd9</DescripcionDetalle>
                    <Cantidad>2</Cantidad>
                    <ImporteUnitario>18.15</ImporteUnitario>
                    <ImporteTotal>43.92</ImporteTotal>
                </IDDetalleFactura>
                <IDDetalleFactura>
                    <DescripcionDetalle>13IY8CORgyRBlfn8uNOuT3dDsXZKyuOS0KuJEB3apcLmcolK6CN7kYZ96Cs3Hky1JprfvPKBig2rzKJF7J6G1MrQOpREUnBZkn9Azulz5lf</DescripcionDetalle>
                    <Cantidad>1</Cantidad>
                    <ImporteUnitario>98.16</ImporteUnitario>
                    <ImporteTotal>117.59</ImporteTotal>
                    <Descuento>0.98</Descuento>
                </IDDetalleFactura>
                <IDDetalleFactura>
                    <DescripcionDetalle>BQLeIwWBor9HsuvVVKyZtrtAmC7WAFL0yfSMtOxbznaJgmWGItngCW458uALHtGtg7jSyKhB0t5WjARohKE1cYJevuIWdu8MmS1mQ0hBz4CH7d2nkPCbOO33qeP1IypkMcFwipFQ6N4MS3zF3NU0tv4gz4CQlp9a3Evwo82rcmyeXLXNcDZDCi8VeuaN7yrDSyecaF</DescripcionDetalle>
                    <Cantidad>2</Cantidad>
                    <ImporteUnitario>76.67</ImporteUnitario>
                    <ImporteTotal>61.23</ImporteTotal>
                    <Descuento>102.74</Descuento>
                </IDDetalleFactura>
                <IDDetalleFactura>
                    <DescripcionDetalle>i3xp4RLnZTKoUtBdW8Mm7MwSXrHPurtLgj47U5sVuAyo34JY4f6iRmy2Nna96kDtMFvYX80QzkQ84tyLVu46Uk47YZUWkImCix4DpVWEmb6CQi1RwVbSyEZBNeNLMbccLsHMUyPPp7El9qgxph70HjCdqXdZEkar8GU2XHIrb6OFo8UujYao3xq9LyzVisqC9ZuOKNz1FwLxKCphsuOux48ykWOim</DescripcionDetalle>
                    <Cantidad>2</Cantidad>
                    <ImporteUnitario>49.53</ImporteUnitario>
                    <ImporteTotal>119.86</ImporteTotal>
                </IDDetalleFactura>
                <IDDetalleFactura>
                    <DescripcionDetalle>8MwLYjtKV3Z09RRHbNuO8cPZdvaxJDEgtrSvMZ2C6n62oSAySZYTPpI7gTs3LtcDEChAt1Qswva2pAntHnQZSHVfQ7IYV4hBEdnJfY0wqkMGoCcGQVnSvZnh4X4QlthoPqcAgq</DescripcionDetalle>
                    <Cantidad>2</Cantidad>
                    <ImporteUnitario>77.52</ImporteUnitario>
                    <ImporteTotal>93.8</ImporteTotal>
                    <Descuento>77.52</Descuento>
                </IDDetalleFactura>
                <IDDetalleFactura>
                    <DescripcionDetalle>LKpyV9WGzZ04hEKlJctA7ovQOu6rBMJAfpjmvUNneXEhgIWxrZQ2Fbq1pLCu1EHK2fCSI15ePAbBPW1kwB8f0yeSpAX5WkBOb6tKEi14J9rALu1CAlk9IuuCGWZEYTB2qxh6cVgNd6vQNu91yZWGoMQYHArOrp4WU5Oux1mNF</DescripcionDetalle>
                    <Cantidad>2</Cantidad>
                    <ImporteUnitario>55</ImporteUnitario>
                    <ImporteTotal>49.25</ImporteTotal>
                    <Descuento>69.3</Descuento>
                </IDDetalleFactura>
                <IDDetalleFactura>
                    <DescripcionDetalle>ijLHyQ9X74OExJ5SpStt4UagjxgJFQ3VgCT5ZxY1FSGaO4Jc6kLlUxIVXmEITB8jWdnBwm7yBZpYqQ1RwF12R8LTCFjOXuTF9G7d11xgya04VZfR5O5iFhzmVYzU9flfZ0GXJE9e61hQolYNwBBtwi7RJ8eDN</DescripcionDetalle>
                    <Cantidad>2</Cantidad>
                    <ImporteUnitario>93.73</ImporteUnitario>
                    <ImporteTotal>226.83</ImporteTotal>
                </IDDetalleFactura>
                <IDDetalleFactura>
                    <DescripcionDetalle>FvGfRWpmnVlbE2fOsh1sje5Vjm4ZkGHTuSotVeLRZNknPVQ0ZN3RDDMjN2YO85NjoJdnMInOQTHVc8v5G9c9El9PziQ</DescripcionDetalle>
                    <Cantidad>1</Cantidad>
                    <ImporteUnitario>3.28</ImporteUnitario>
                    <ImporteTotal>1.08</ImporteTotal>
                    <Descuento>2.39</Descuento>
                </IDDetalleFactura>
                <IDDetalleFactura>
                    <DescripcionDetalle>90bfzkIAFNPSyv</DescripcionDetalle>
                    <Cantidad>2</Cantidad>
                    <ImporteUnitario>18.57</ImporteUnitario>
                    <ImporteTotal>44.94</ImporteTotal>
                </IDDetalleFactura>
                <IDDetalleFactura>
                    <DescripcionDetalle>uKMiN4IiTXHc2qXF5eWLCQauoW99yjEILoiyIcNF3Q2Stzzt2FhsGOQxKMdaZ2gEPwyDdCoh</DescripcionDetalle>
                    <Cantidad>1</Cantidad>
                    <ImporteUnitario>45.25</ImporteUnitario>
                    <ImporteTotal>54.75</ImporteTotal>
                </IDDetalleFactura>
                <IDDetalleFactura>
                    <DescripcionDetalle>YyGT1yCjQejUvIC1</DescripcionDetalle>
                    <Cantidad>2</Cantidad>
                    <ImporteUnitario>46.56</ImporteUnitario>
                    <ImporteTotal>112.68</ImporteTotal>
                </IDDetalleFactura>
                <IDDetalleFactura>
                    <DescripcionDetalle>yCg6cLo5DZOIepFDOPPntrWBPli9okAaROoEzLgNeZUQZDFAE6v4auAAhiDCqVpd5Ri4dgIakPzLsgymVWuZy10c1JXglHAOOsqFdCSfpbplOAO8g8doq1vNe8swBv4ij83YQAiGDUBkrTcAHHUGrr8BKk1MhOFkCniEya20V2p66HCLpZhyaNfWjbdwkXtuPqEheftK3ZVMINeDbtgEjTQ44rgGM0Td6oM5s0iKvzfIS7</DescripcionDetalle>
                    <Cantidad>2</Cantidad>
                    <ImporteUnitario>66.37</ImporteUnitario>
                    <ImporteTotal>120.46</ImporteTotal>
                    <Descuento>33.19</Descuento>
                </IDDetalleFactura>
                <IDDetalleFactura>
                    <DescripcionDetalle>ybD1NpZoECH55LoiKJcZswZqPD0IgpURfVgNJoXNfaoH7je9jwmzpwB3Clgi6TVSOJ8YaXEEWRhbdARLTAAIUt2oy4Jlwgwn5XwiPTeEArlKKuAGqQXrVkUsSGzkbNsBZ7juNR50oHtZgl0</DescripcionDetalle>
                    <Cantidad>1</Cantidad>
                    <ImporteUnitario>73.7</ImporteUnitario>
                    <ImporteTotal>89.18</ImporteTotal>
                </IDDetalleFactura>
                <IDDetalleFactura>
                    <DescripcionDetalle>WAYEzfCM7df7JXHbRHyLc1wtX2RuIjIKjk9</DescripcionDetalle>
                    <Cantidad>2</Cantidad>
                    <ImporteUnitario>92.12</ImporteUnitario>
                    <ImporteTotal>222.93</ImporteTotal>
                </IDDetalleFactura>
                <IDDetalleFactura>
                    <DescripcionDetalle>LXoil5qoC50sB</DescripcionDetalle>
                    <Cantidad>2</Cantidad>
                    <ImporteUnitario>18.92</ImporteUnitario>
                    <ImporteTotal>6.41</ImporteTotal>
                    <Descuento>32.54</Descuento>
                </IDDetalleFactura>
                <IDDetalleFactura>
                    <DescripcionDetalle>vmU4E6Ng5LqJU1Q8IVjDNp27wXjq6K17h2irr3aVNVLXqzrbbokmAzMWtZnhdcBNUO6WS</DescripcionDetalle>
                    <Cantidad>2</Cantidad>
                    <ImporteUnitario>10.36</ImporteUnitario>
                    <ImporteTotal>25.07</ImporteTotal>
                </IDDetalleFactura>
                <IDDetalleFactura>
                    <DescripcionDetalle>3oDRMtfFk7aN5Drg7ihLkCnvazLJCrwX0sJPT9m</DescripcionDetalle>
                    <Cantidad>2</Cantidad>
                    <ImporteUnitario>68.17</ImporteUnitario>
                    <ImporteTotal>49.49</ImporteTotal>
                    <Descuento>95.44</Descuento>
                </IDDetalleFactura>
                <IDDetalleFactura>
                    <DescripcionDetalle>hGz9UZMuEiDjk7MhZfZ7uSfu7um59NrHRhR41lsJda7NckP7toES57he0L0hlXWT</DescripcionDetalle>
                    <Cantidad>2</Cantidad>
                    <ImporteUnitario>44.96</ImporteUnitario>
                    <ImporteTotal>108.8</ImporteTotal>
                </IDDetalleFactura>
                <IDDetalleFactura>
                    <DescripcionDetalle>YlPnJa61hZLDAyh0fY8POex9v3Pi9T1OxVF0AAeq4aIEi16SvEJdltlYQMbGAgGUTdkZKJptX2QAhZmWxrPH1xE59w5ZV8fl8bycc1M7iWBZZdK6CeZvzZYkycZNjEEPxumGKKNTpRpAF1FrUPkQbWAmdKHzUVOUyvTXyheP0gfHFo3qI6jNx9oQuSqGRS0tsIQti8YJCRhlehGPwGALouXCykOW9ClOU5A6Cn4C1Mi4FzmPX</DescripcionDetalle>
                    <Cantidad>2</Cantidad>
                    <ImporteUnitario>24.45</ImporteUnitario>
                    <ImporteTotal>59.17</ImporteTotal>
                </IDDetalleFactura>
            </DetallesFactura>
            <ImporteTotalFactura>6946.97</ImporteTotalFactura>
            <FechaOperacion>30-06-2013</FechaOperacion>
            <RetencionSoportada>77572.29</RetencionSoportada>
            <BaseImponibleACoste>44963.28</BaseImponibleACoste>
            <Claves>
                <IDClave>
                    <ClaveRegimenIvaOpTrascendencia>09</ClaveRegimenIvaOpTrascendencia>
                </IDClave>
            </Claves>
        </DatosFactura>
        <TipoDesglose>
            <DesgloseFactura>
                <Sujeta>
                    <Exenta>
                        <DetalleExenta>
                            <CausaExencion>E6</CausaExencion>
                            <BaseImponible>203.98000000000002</BaseImponible>
                        </DetalleExenta>
                        <DetalleExenta>
                            <CausaExencion>E1</CausaExencion>
                            <BaseImponible>318.26</BaseImponible>
                        </DetalleExenta>
                        <DetalleExenta>
                            <CausaExencion>E3</CausaExencion>
                            <BaseImponible>11.89</BaseImponible>
                        </DetalleExenta>
                        <DetalleExenta>
                            <CausaExencion>E4</CausaExencion>
                            <BaseImponible>168.45</BaseImponible>
                        </DetalleExenta>
                        <DetalleExenta>
                            <CausaExencion>E5</CausaExencion>
                            <BaseImponible>61.23</BaseImponible>
                        </DetalleExenta>
                    </Exenta>
                    <NoExenta>
                        <DetalleNoExenta>
                            <TipoNoExenta>S1</TipoNoExenta>
                            <DesgloseIVA>
                                <DetalleIVA>
                                    <BaseImponible>3384.60</BaseImponible>
                                    <TipoImpositivo>21</TipoImpositivo>
                                    <CuotaImpuesto>710.77</CuotaImpuesto>
                                </DetalleIVA>
                            </DesgloseIVA>
                        </DetalleNoExenta>
                    </NoExenta>
                </Sujeta>
                <NoSujeta>
                    <DetalleNoSujeta>
                        <Causa>OT</Causa>
                        <Importe>1182.50</Importe>
                    </DetalleNoSujeta>
                    <DetalleNoSujeta>
                        <Causa>RL</Causa>
                        <Importe>18487.82</Importe>
                    </DetalleNoSujeta>
                </NoSujeta>
            </DesgloseFactura>
        </TipoDesglose>
    </Factura>
    <HuellaTBAI Id="_9651">
        <Software>
            <LicenciaTBAI>N5KwFhSaxjQ</LicenciaTBAI>
            <EntidadDesarrolladora>
                <NIF>55319949G</NIF>
            </EntidadDesarrolladora>
            <Nombre>HJEJ32kn6VAerLgXgygWQQ4N056Re</Nombre>
            <Version>BNFQxqy</Version>
        </Software>
    </HuellaTBAI>
<Signature xmlns="http://www.w3.org/2000/09/xmldsig#"><SignedInfo><CanonicalizationMethod Algorithm="http://www.w3.org/2001/10/xml-exc-c14n#"/><SignatureMethod Algorithm="http://www.w3.org/2000/09/xmldsig#rsa-sha1"/><Reference URI="#_9648"><Transforms><Transform Algorithm="http://www.w3.org/2001/10/xml-exc-c14n#"/></Transforms><DigestMethod Algorithm="http://www.w3.org/2000/09/xmldsig#sha1"/><DigestValue>zO8pzh3R5mLi8m8r6+QhIbUXNno=</DigestValue></Reference><Reference URI="#_9649"><Transforms><Transform Algorithm="http://www.w3.org/2001/10/xml-exc-c14n#"/></Transforms><DigestMethod Algorithm="http://www.w3.org/2000/09/xmldsig#sha1"/><DigestValue>7+RwbuCsVlQMxfVq+xaz9uR7zzk=</DigestValue></Reference><Reference URI="#_9650"><Transforms><Transform Algorithm="http://www.w3.org/2001/10/xml-exc-c14n#"/></Transforms><DigestMethod Algorithm="http://www.w3.org/2000/09/xmldsig#sha1"/><DigestValue>dditeOIVRbyanYc/XaxLH0Sw7Ms=</DigestValue></Reference><Reference URI="#_9651"><Transforms><Transform Algorithm="http://www.w3.org/2001/10/xml-exc-c14n#"/></Transforms><DigestMethod Algorithm="http://www.w3.org/2000/09/xmldsig#sha1"/><DigestValue>EtfH4J+SHQK8kEyuYV6DnirjK6Q=</DigestValue></Reference></SignedInfo><SignatureValue>EF0snhtnkXKgHEAadEX66gFZlT5NgwguMbIc0LB+dvXI3Kz4g0fZReU0LUR6ds3UmK5iMcm4KCk9JmeH5jc0pTh9UHwdqq13qKg67qjWA/hUOl+QgaCv9JnNDMH+TlJVtF7WawUXo0/dxxfn3TEv+lY5XHWKDDrWIB+UcnKvyqptW03yeI2XjR/pNyhfjnEsTZLC85IjipdVvhUniuauwNUmTqTrO/TKjblA5sseXV6EVFUEmGGdXeohsJ/I7UuTOo2QO9QTi/Q7Xsdq9AJTrz1AY794n1XdzKJzqzPbwNMt9m0zVRjEBe+1mr/mJUO9z4pEkxDFwbEPHj6ouuvaow==</SignatureValue></Signature></T:TicketBai>