<?xml version="1.0" encoding="utf-8"?>
<T:TicketBai xmlns:ds="http://www.w3.org/2000/09/xmldsig#" xmlns:T="urn:ticketbai:emision" xmlns:xsi="http://www.w3.org/2001/XMLSchema-instance" xsi:schemaLocation="http://www.w3.org/2001/XMLSchema ticketBai_schema.xsd">
    <Cabecera Id="_10452">
        <IDVersionTBAI>1.2</IDVersionTBAI>
    </Cabecera>
    <Sujetos Id="_10453">
        <Emisor>
            <NIF>87741701J</NIF>
            <ApellidosNombreRazonSocial>the dow chemical company</ApellidosNombreRazonSocial>
        </Emisor>
        <Destinatarios>
            <IDDestinatario>
                <IDOtro>
                    <IDType>05</IDType>
                    <ID>HXVoeBGr</ID>
                </IDOtro>
                <ApellidosNombreRazonSocial>mV1SHM3a8Ctg9vXemz98EAtJ0zN5c8rXqlVQJIQRGdcILVuKgrSpFrra5D4cO8NGozTYsuvNsOX87czbczECh2OBlOf</ApellidosNombreRazonSocial>
                <CodigoPostal>BW3qOyNAVqyiTwUZ</CodigoPostal>
                <Direccion>rFDIgaddpzjBHXI3leN6cr9N25ZYUZo9qCzSvBcO395HpQe0qkCn3BvZ5jmteNsjChl7OFX5RJ2VlIeRN</Direccion>
            </IDDestinatario>
        </Destinatarios>
        <VariosDestinatarios>S</VariosDestinatarios>
        <EmitidaPorTercerosODestinatario>N</EmitidaPorTercerosODestinatario>
    </Sujetos>
    <Factura Id="_10454">
        <CabeceraFactura>
            <NumFactura>79148</NumFactura>
            <FechaExpedicionFactura>19-05-2021</FechaExpedicionFactura>
            <HoraExpedicionFactura>16:20:17</HoraExpedicionFactura>
            <SerieFactura>jjcNoYm8s</SerieFactura>
            <FacturaEmitidaSustitucionSimplificada>S</FacturaEmitidaSustitucionSimplificada>
        </CabeceraFactura>
        <DatosFactura>
            <DescripcionFactura>pJ4</DescripcionFactura>
            <DetallesFactura>
                <IDDetalleFactura>
                    <DescripcionDetalle>WI2boMXFYhRlmOx16EfAQCyHrK4KiUZGPw68tf08gs4Z538VuHRhltSOdGW0ZOKRBZAZO61LdJw4PKifgd36HX8bSmGbIpfIkLQsOuxgirjToyEHUnI9KF51x7VBOVc3IGXzQvLSn0urgBNGvATCiHX3pcb</DescripcionDetalle>
                    <Cantidad>1</Cantidad>
                    <ImporteUnitario>88.4</ImporteUnitario>
                    <ImporteTotal>55.62</ImporteTotal>
                    <Descuento>42.43</Descuento>
                </IDDetalleFactura>
                <IDDetalleFactura>
                    <DescripcionDetalle>5SpoA1ObxvevnwcaV0P5DEx8WW9PhRPedlzwCHqdJgmMsZRkhcGI04fgi26ddxLqSijYHdR2BcJ7DSSFLS3LY64avrZkGTYyPHi</DescripcionDetalle>
                    <Cantidad>2</Cantidad>
                    <ImporteUnitario>89.1</ImporteUnitario>
                    <ImporteTotal>109.96</ImporteTotal>
                    <Descuento>87.32</Descuento>
                </IDDetalleFactura>
                <IDDetalleFactura>
                    <DescripcionDetalle>IN5YZPhaUmqSMrb4L9s9f6WucPV981txcWYtFS4JxRkc39OZes2OPAawY7zP9ZxyOkzKPVWngQSg2hi8CJr1o3wkWnil9GoHs84f2</DescripcionDetalle>
                    <Cantidad>1</Cantidad>
                    <ImporteUnitario>26.82</ImporteUnitario>
                    <ImporteTotal>29.85</ImporteTotal>
                    <Descuento>2.15</Descuento>
                </IDDetalleFactura>
                <IDDetalleFactura>
                    <DescripcionDetalle>yZ3lbyQkrvVEjE3ZOdGUIaBgzJxRQ3X63l5d7XZAQxKBkqRaLKhNzy4h4PKjfLbf5xCA75HqwDSpICdbq5gjXsuC1raP7JBqImDzUXQQfd9lvPc</DescripcionDetalle>
                    <Cantidad>1</Cantidad>
                    <ImporteUnitario>46.37</ImporteUnitario>
                    <ImporteTotal>56.11</ImporteTotal>
                </IDDetalleFactura>
                <IDDetalleFactura>
                    <DescripcionDetalle>CPB4pLbaERhlo7r8Ho9VdxqARmdadT</DescripcionDetalle>
                    <Cantidad>2</Cantidad>
                    <ImporteUnitario>49.93</ImporteUnitario>
                    <ImporteTotal>83.37</ImporteTotal>
                    <Descuento>30.96</Descuento>
                </IDDetalleFactura>
                <IDDetalleFactura>
                    <DescripcionDetalle>jlhsrQTbSzmNIR0RrOMxjto11H98nfXyCUl2gttm9GzMyIZ1</DescripcionDetalle>
                    <Cantidad>2</Cantidad>
                    <ImporteUnitario>96.95</ImporteUnitario>
                    <ImporteTotal>0</ImporteTotal>
                    <Descuento>193.9</Descuento>
                </IDDetalleFactura>
                <IDDetalleFactura>
                    <DescripcionDetalle>RtfufLoU2xhO79pjTU9gGEb1FTh0FaczbY9oMKygjiYZABN7Xx826OeFyrkstf</DescripcionDetalle>
                    <Cantidad>1</Cantidad>
                    <ImporteUnitario>4.88</ImporteUnitario>
                    <ImporteTotal>5.9</ImporteTotal>
                </IDDetalleFactura>
                <IDDetalleFactura>
                    <DescripcionDetalle>Bt0YPRw9ddI1kvyAY0KGYQ66b2mW9D37ds7ZE8fiKQ2h80K0Wb3WnuOK2HjvPS2tlJb89FiQjBkQ442pkOcIxqWrCbJGp91xbWU1m7Hl65lNym9gegET6sGGXmGxXHlYcXVJIeykTeUiC92sXPXnH6pbuD31i3x3LBY6NK61GnkutjuPqkzys</DescripcionDetalle>
                    <Cantidad>2</Cantidad>
                    <ImporteUnitario>17.78</ImporteUnitario>
                    <ImporteTotal>43.03</ImporteTotal>
                </IDDetalleFactura>
                <IDDetalleFactura>
                    <DescripcionDetalle>xC9526zTb9eHur81tOUPLeVgR0VuZgKnFKlirbkoPXZjSgH9gqmfvVD4FTmDVEYo4v8g8DVtiPP6xgcyUI0rpn4Tz8T984oXaK2dzT4xii2UhPFbbfuRheThFfaaPij2ymAqG0kSYiM</DescripcionDetalle>
                    <Cantidad>1</Cantidad>
                    <ImporteUnitario>11.01</ImporteUnitario>
                    <ImporteTotal>13.32</ImporteTotal>
                </IDDetalleFactura>
                <IDDetalleFactura>
                    <DescripcionDetalle>crfFQF3fRiJkk9JKdwHfdUigXpXa</DescripcionDetalle>
                    <Cantidad>2</Cantidad>
                    <ImporteUnitario>25.01</ImporteUnitario>
                    <ImporteTotal>52.66</ImporteTotal>
                    <Descuento>6.5</Descuento>
                </IDDetalleFactura>
                <IDDetalleFactura>
                    <DescripcionDetalle>n9JvAGlX0S2MYoquwZN26c1NU5FM9eI0JKCvhROYsmF5KRQIu1gSJfV60ZLM90F6nd0gPJ46OaPPxGajYcWppth7tgTEGqUTsP</DescripcionDetalle>
                    <Cantidad>2</Cantidad>
                    <ImporteUnitario>96.49</ImporteUnitario>
                    <ImporteTotal>233.51</ImporteTotal>
                </IDDetalleFactura>
                <IDDetalleFactura>
                    <DescripcionDetalle>UfDFZIfB2pVpNH09lsdbIQxLIwFYlzvliOeZZvGIX83rL0W82bjKf</DescripcionDetalle>
                    <Cantidad>1</Cantidad>
                    <ImporteUnitario>19.98</ImporteUnitario>
                    <ImporteTotal>24.18</ImporteTotal>
                </IDDetalleFactura>
                <IDDetalleFactura>
                    <DescripcionDetalle>FQentjpIpIokNhfCz1vbVlQDj26Z09wX6SXxxjK8F4bael7fkLT306GpbnE8S3j</DescripcionDetalle>
                    <Cantidad>1</Cantidad>
                    <ImporteUnitario>6.48</ImporteUnitario>
                    <ImporteTotal>7.84</ImporteTotal>
                </IDDetalleFactura>
                <IDDetalleFactura>
                    <DescripcionDetalle>oXp6VaMtwclgMln5UzDWMfpmQX70fSA22i9gFoaLjB0EBZ47kr9YgaW8Fkeut606wfELjvAdT80ptscOtBH8jfUst67eBjEc4Jt5fXYh9Wm2QmsRVl4aRDMn9tbWye4qNM4Qxb7</DescripcionDetalle>
                    <Cantidad>1</Cantidad>
                    <ImporteUnitario>94.66</ImporteUnitario>
                    <ImporteTotal>6.87</ImporteTotal>
                    <Descuento>88.98</Descuento>
                </IDDetalleFactura>
                <IDDetalleFactura>
                    <DescripcionDetalle>b8mitJEaMZCVn1ajLesuOkgatyLzoN72fePxAvC5Np0K6yYwmdMCEvK36c5NrNjCJ5BOSBk9P2fHnPYwDcCK5gMGKMwoA85Y8xp6msuf0R3H0snAyjQ6N9KJvWpPqeXLNyBrDEiL3yfH9L0mEEBenHp2pM8Ff5jnGF2ziDKq55JeEHpebkvxWcuWkuKXMNvJJ2W7t98PooANEY2rsFJKfSPC</DescripcionDetalle>
                    <Cantidad>2</Cantidad>
                    <ImporteUnitario>23.83</ImporteUnitario>
                    <ImporteTotal>57.67</ImporteTotal>
                </IDDetalleFactura>
                <IDDetalleFactura>
                    <DescripcionDetalle>KWmhT5TL5b6SD9qJaY8pWDeBWLffbzrC2TUJrQLLVSr14TeincoUMJsX0XNZcIg8vHxeBn</DescripcionDetalle>
                    <Cantidad>2</Cantidad>
                    <ImporteUnitario>16.4</ImporteUnitario>
                    <ImporteTotal>26.98</ImporteTotal>
                    <Descuento>10.5</Descuento>
                </IDDetalleFactura>
                <IDDetalleFactura>
                    <DescripcionDetalle>gnipxkeo4QWVzgP0cAD964G5xxwI1xTJ6YqONECbEHsn41nSlqGELnUcy2M8UHY0YdrgHInVp8JWARQEBVedBg</DescripcionDetalle>
                    <Cantidad>1</Cantidad>
                    <ImporteUnitario>29.93</ImporteUnitario>
                    <ImporteTotal>1.45</ImporteTotal>
                    <Descuento>28.73</Descuento>
                </IDDetalleFactura>
                <IDDetalleFactura>
                    <DescripcionDetalle>V1PVhhd3kCbsqZV1fEGLBERLqEheLT1ckFXAbiCuNPFIeC7F5zOtx7U3hIh63qKUBdxgJoC43jMFpbt9djswHU7Ludz3f6DhlQNqjGV9xeMbwAXhyi5yi</DescripcionDetalle>
                    <Cantidad>1</Cantidad>
                    <ImporteUnitario>78.8</ImporteUnitario>
                    <ImporteTotal>95.35</ImporteTotal>
                </IDDetalleFactura>
                <IDDetalleFactura>
                    <DescripcionDetalle>fvCC0GG1iz7NtLeuy61rXhFFk1JXf5GqRs5yiJjQ7MOmhujKXTdQCLsTZF76CjRA7l80pJr8rbFwy8q4CVRBVTALNzLuySXI10h7JMPA5XAifMuVbmc7m7BdqBUfkvkL7WOOF3L2nz6EkUiel1rWLRwI1CBGr5uoDDhrbvrcXQeynWdqdlYayaJTfAyrqwYyYmGpS</DescripcionDetalle>
                    <Cantidad>1</Cantidad>
                    <ImporteUnitario>24.04</ImporteUnitario>
                    <ImporteTotal>21.24</ImporteTotal>
                    <Descuento>6.49</Descuento>
                </IDDetalleFactura>
                <IDDetalleFactura>
                    <DescripcionDetalle>L5F78wVtlonsX8MjOBoQLUvjrCZuDexMqXIVFxcTRbXwGlhkjuNnYmftHiC7j3biBvgjPa5vDzcY5DihKcAtpWTiBSZRm8DUOd7LqCnRA5tNR398vvDoeNFU2NXbCC49HoV8</DescripcionDetalle>
                    <Cantidad>1</Cantidad>
                    <ImporteUnitario>69.24</ImporteUnitario>
                    <ImporteTotal>83.78</ImporteTotal>
                </IDDetalleFactura>
                <IDDetalleFactura>
                    <DescripcionDetalle>JcQMl1HdTSOv4Em7xhR4aKCdtrKp6rEXVgQmpMTat9xhktrxZXT8nYJi</DescripcionDetalle>
                    <Cantidad>2</Cantidad>
                    <ImporteUnitario>8.91</ImporteUnitario>
                    <ImporteTotal>7.97</ImporteTotal>
                    <Descuento>11.23</Descuento>
                </IDDetalleFactura>
                <IDDetalleFactura>
                    <DescripcionDetalle>MnQvcA1D4HaqA62GpiAYJeAroFygKtORAOviHkfDb8xKe7OQbZAxR24wSJptWmdvxwS7i3kqzXrNSGT7bhHNh95xxlP41ckdeXgDTiGrqhzKPEypWyQhvgwHZdTKTXSMFmrRDQ5nOO2UgGMuy8pMEwEAuHFtSxZxoBiHCCXU2Ln3APwbR22vx3JQGPjuUIDWlTAdz2SsVAFMrkwmSf3Zcda5qimlI8p1oIAU2dc4imm</DescripcionDetalle>
                    <Cantidad>2</Cantidad>
                    <ImporteUnitario>74.51</ImporteUnitario>
                    <ImporteTotal>19.83</ImporteTotal>
                    <Descuento>132.63</Descuento>
                </IDDetalleFactura>
                <IDDetalleFactura>
                    <DescripcionDetalle>yFCMBEpZTJ9mFa5hcLYlUJspyhYge0WG7Wqjx1bW7VsZVp8dcsqAA0TsxYxNcmWNFWzHCwr0zlmnJJ</DescripcionDetalle>
                    <Cantidad>2</Cantidad>
                    <ImporteUnitario>24.53</ImporteUnitario>
                    <ImporteTotal>20.78</ImporteTotal>
                    <Descuento>31.89</Descuento>
                </IDDetalleFactura>
                <IDDetalleFactura>
                    <DescripcionDetalle>wgxHGfhNK21Qf4dl35Dsgp3Ub2Y0R0jyYSNhvt4VhfGBIYllfWUoB3RNNscSpa</DescripcionDetalle>
                    <Cantidad>2</Cantidad>
                    <ImporteUnitario>17.81</ImporteUnitario>
                    <ImporteTotal>4.31</ImporteTotal>
                    <Descuento>32.06</Descuento>
                </IDDetalleFactura>
                <IDDetalleFactura>
                    <DescripcionDetalle>AOqXA4PFzjd1o5ZsIQYZJaSfDGN9dTVf3DvWQBYq0U8pVPMHBM09uJEjJ76SE76wwoiKWsjvntqBlThgnoQwCkYvgq3i3l42CbvJiSp28AyLu1TulKBVuojuEIytekjHdAYoDQlcQHvmi8</DescripcionDetalle>
                    <Cantidad>1</Cantidad>
                    <ImporteUnitario>88.25</ImporteUnitario>
                    <ImporteTotal>37.38</ImporteTotal>
                    <Descuento>57.36</Descuento>
                </IDDetalleFactura>
                <IDDetalleFactura>
                    <DescripcionDetalle>0c3fSdEEssY5l8fESyKx3OEVTGMMSJhwSH5qqAYSOZsg2EhUB9Tw1Jdy1uZSF4bpeLdorF9WJvdmqEIRV7L52psOPDdrono6613viVeQ9XRuuKARv5gHol1E3Dgvqdk1HyXVtnKeOUvuxCiti8ChzZB7TXxF9uUhxyc6RUJauG5ZddOa9xFsvDksQ1j76GbI4vaElVfDejO8Uz</DescripcionDetalle>
                    <Cantidad>2</Cantidad>
                    <ImporteUnitario>69.88</ImporteUnitario>
                    <ImporteTotal>25.36</ImporteTotal>
                    <Descuento>118.8</Descuento>
                </IDDetalleFactura>
                <IDDetalleFactura>
                    <DescripcionDetalle>v5x</DescripcionDetalle>
                    <Cantidad>1</Cantidad>
                    <ImporteUnitario>62.88</ImporteUnitario>
                    <ImporteTotal>76.08</ImporteTotal>
                </IDDetalleFactura>
                <IDDetalleFactura>
                    <DescripcionDetalle>lveBQs5TIaGxmLsgOdjUhWNQ46gfAVn20iEqPOrskOE0V3QCFucMHHDoKkM2NQjzSVpUPv3wHjZ0D6IlXdUMMMzlHwtTN5z9XzYTmnnuqTf9mMGMUZe2</DescripcionDetalle>
                    <Cantidad>1</Cantidad>
                    <ImporteUnitario>79.29</ImporteUnitario>
                    <ImporteTotal>61.41</ImporteTotal>
                    <Descuento>28.54</Descuento>
                </IDDetalleFactura>
                <IDDetalleFactura>
                    <DescripcionDetalle>7ZOuFQeuem3XxL36UdLZxqdIjRbPG5JhKnKddUtWREYImiw36CEIRAtk365tW2JtVaO1wRrVFEPSXcH7SPbg2Msms5ldLWoSZWLdvO692kQl9Br12Qtfnd2hFkCyNp</DescripcionDetalle>
                    <Cantidad>1</Cantidad>
                    <ImporteUnitario>78.71</ImporteUnitario>
                    <ImporteTotal>95.24</ImporteTotal>
                </IDDetalleFactura>
                <IDDetalleFactura>
                    <DescripcionDetalle>VCcmOF8z66mrmHdmGFNEKGEP1JpYC8sO3bqw2sHwMa4t8oC8Stw9bb0QDCpPJ340KlY9WtXyG</DescripcionDetalle>
                    <Cantidad>1</Cantidad>
                    <ImporteUnitario>10.45</ImporteUnitario>
                    <ImporteTotal>11.25</ImporteTotal>
                    <Descuento>1.15</Descuento>
                </IDDetalleFactura>
                <IDDetalleFactura>
                    <DescripcionDetalle>zJZZnCGbJY0bPqLgxSbpHnua7MEuFjqgAkyKiQEhb9iCpHYXyrw1RpmAB3fslEqeEyQf6lEWxFQ96eMm3uMgoZN1AsoK0V9g5wpOulxm8AHtsJqLfJfTECXg6zbfgm0tT3rBapdf4e2irC8QdlXkzEC9SnLyxK3iUG1wyBLLqVXV19KiFUx3lctvLte37vqtC05ztYT4ZU4YhZA26vZzLxTTvqjt1UHBqpPxwUsMwJ37UFCmUW7y8H</DescripcionDetalle>
                    <Cantidad>1</Cantidad>
                    <ImporteUnitario>97.4</ImporteUnitario>
                    <ImporteTotal>111.96</ImporteTotal>
                    <Descuento>4.87</Descuento>
                </IDDetalleFactura>
                <IDDetalleFactura>
                    <DescripcionDetalle>A45jPdnIw4l3ZZ0PtgiqX3LoKdB9LECqLqTCcn4EX67fwbLVzKcAAh0TAPYlVfTGzxbR2OlnOSMmqO9F0ZzMToaxXOrR395S4sSZdwOwkQgXhLgqgtGvZD9xJdA2DdWg967FowFvJCMw9ECEwDYlEgABqmRMwky6h2hsipIHltFnjjwt2KAGZdAv3c0O6jaZwkz8ruerfyLHyzV0TQkDl5mYU2e75vd8hjZqBq4B4nZCxUwnefE0</DescripcionDetalle>
                    <Cantidad>2</Cantidad>
                    <ImporteUnitario>44.07</ImporteUnitario>
                    <ImporteTotal>90.65</ImporteTotal>
                    <Descuento>13.22</Descuento>
                </IDDetalleFactura>
                <IDDetalleFactura>
                    <DescripcionDetalle>op4PasGiXeJ8USr3oLcr5QgYb0fXcMwG5xQlK</DescripcionDetalle>
                    <Cantidad>2</Cantidad>
                    <ImporteUnitario>6.26</ImporteUnitario>
                    <ImporteTotal>0.16</ImporteTotal>
                    <Descuento>12.39</Descuento>
                </IDDetalleFactura>
                <IDDetalleFactura>
                    <DescripcionDetalle>m2XEmmcCsfo8y37BDRsHBnfIXOPSyCUcpouQrb0Fhuf703PfOZWWzqF3rxm4YDu7fN2sO9UhX0k0uIHxNc424F10pqorGXfnUquwbNrqdBTAWweUH4IqqkhxJIevcekkuMGQPKoO3FNVHthLCh1Mf9iw0P33JEhWoUqPlexshUPh4ow0FOgNWTIsLLFOMUMKtx2tBUmm8hiSTrq2mHiL8ZHhVdpeSFLfQWn3nSEMMBGSdVjefhw1ZcvB</DescripcionDetalle>
                    <Cantidad>2</Cantidad>
                    <ImporteUnitario>81.52</ImporteUnitario>
                    <ImporteTotal>104.56</ImporteTotal>
                    <Descuento>76.63</Descuento>
                </IDDetalleFactura>
                <IDDetalleFactura>
                    <DescripcionDetalle>Q4ho1WaEhJ363IAMe3iYrBPVgRjnTFcIF5a1hdXOBNtLQ64hduwDkehIKLkxzG96ewlySnpC2dD3wBggmnqJyfPxsZToIUWJ3ZMb9zobhSh6SpRk4fcJkOf4ukMDzWaS5kZLKXEz6U6oZ59YSpqzJwAAcdV4LgHW1QIPRhdJ2p4z2FDzh5FDPvP5cfhOlJekPGEpUBiCwW7nhbP</DescripcionDetalle>
                    <Cantidad>1</Cantidad>
                    <ImporteUnitario>51.49</ImporteUnitario>
                    <ImporteTotal>61.69</ImporteTotal>
                    <Descuento>0.51</Descuento>
                </IDDetalleFactura>
                <IDDetalleFactura>
                    <DescripcionDetalle>rFFH2gmgZ7Vpjbs3PE3uE8zGz2YryY50BiVMQNWeSGtGFaqG9L1GovkEXkqLSp4dhl2dRlqiIDplmTK0IcKzqKUKCxZqoWZ4joVD2QzC91d0NfSR0A3vFLsCk2Tj3LXtp6zKPpQxtrdvhJAKZdPAd4HLUqJUsVm0xVXWN39XP7vnZ49sgRorA0LWyrUdJPk63QXVzjjTl6wMJb</DescripcionDetalle>
                    <Cantidad>1</Cantidad>
                    <ImporteUnitario>53.18</ImporteUnitario>
                    <ImporteTotal>64.35</ImporteTotal>
                </IDDetalleFactura>
                <IDDetalleFactura>
                    <DescripcionDetalle>DEnBosUPxY5uVya8k1AeP4n9z42GjKVrdq45noBMIGGIrX1zsf1DXtqzZEyqvLYjkszmkxbFB6DWgzL2rw9mcJfCaHkW0etg</DescripcionDetalle>
                    <Cantidad>2</Cantidad>
                    <ImporteUnitario>20.85</ImporteUnitario>
                    <ImporteTotal>50.46</ImporteTotal>
                </IDDetalleFactura>
                <IDDetalleFactura>
                    <DescripcionDetalle>oC6Ygfic2h6JpkjftsATs2ZiUL</DescripcionDetalle>
                    <Cantidad>1</Cantidad>
                    <ImporteUnitario>83.56</ImporteUnitario>
                    <ImporteTotal>60.67</ImporteTotal>
                    <Descuento>33.42</Descuento>
                </IDDetalleFactura>
                <IDDetalleFactura>
                    <DescripcionDetalle>OYiH90IJTzXrev1ikuGS7RVCECYJfcAnzncUq6HPvKRNskpzbcnR9vts5BK1Fbx5X252pDvD0KvSjVH2ONbkPuWw3o0aEo0bKDwzQnxogetf4VNFcugRt7gtDzvaKSaSBVIjP25iER1ML74JrR6K4mrPaPS5I9JjkGiZD3SymfqXfyJGB910uaNb1c4ZC31YLdneGoZFb9obYMb0KDM8fjoDty3Tu1</DescripcionDetalle>
                    <Cantidad>2</Cantidad>
                    <ImporteUnitario>28.54</ImporteUnitario>
                    <ImporteTotal>69.07</ImporteTotal>
                </IDDetalleFactura>
                <IDDetalleFactura>
                    <DescripcionDetalle>j5wS1vz8zBrmGHNknHXEktClmuUrXxEwlgfGlo3Tv2Pkbo8uPbfphmyUTH1UnptP0DVAZoSsPe4OKcYZb7Cd8mfqgdyAy0Tkg83BAJcVoCw6IdM1MSRTr9Kl293GLfYpIqLIuNcQsopuri0WF9wfkhSul50WzEyMoySK1N76QSbcKtwdBf4sY0nA2NVL9p</DescripcionDetalle>
                    <Cantidad>1</Cantidad>
                    <ImporteUnitario>54.67</ImporteUnitario>
                    <ImporteTotal>41.67</ImporteTotal>
                    <Descuento>20.23</Descuento>
                </IDDetalleFactura>
                <IDDetalleFactura>
                    <DescripcionDetalle>delzqReQq63GQbN6Hs18o9PCJzRf9lJWfAf</DescripcionDetalle>
                    <Cantidad>1</Cantidad>
                    <ImporteUnitario>74.97</ImporteUnitario>
                    <ImporteTotal>37.2</ImporteTotal>
                    <Descuento>44.23</Descuento>
                </IDDetalleFactura>
                <IDDetalleFactura>
                    <DescripcionDetalle>L1c9CJtNeYIfjMRyB4mZmR0KCN21p8YdyTFRzDXfyv5RDR9b70HBMKrHcAWVjORcsFc15pzhzoHRRTc4ikWAFxSRgrs</DescripcionDetalle>
                    <Cantidad>2</Cantidad>
                    <ImporteUnitario>39.2</ImporteUnitario>
                    <ImporteTotal>94.86</ImporteTotal>
                </IDDetalleFactura>
                <IDDetalleFactura>
                    <DescripcionDetalle>wvN6aluAc6qHOPNNaCDSZ7aHp6C3hVqaarWIzOfw0vP7Kj8DbRQGoHBLqt3v7qsTeoChJYJfr30X6OTbuuiRUw2Mjhh4P6UUVnRHmHyoLpd6SAScmvgj8MdRzLR8flin9lwUdd0t51PkkV9mGDXk5XiudAfD6k5sQhslajaxD4KQd26NRiZLeprsbnyMSPGs11sfWeHtsxddYhoPBDEdafBY3dbVlO28pQj8h8yyYUF7xOfzaPNF</DescripcionDetalle>
                    <Cantidad>2</Cantidad>
                    <ImporteUnitario>62.11</ImporteUnitario>
                    <ImporteTotal>27.06</ImporteTotal>
                    <Descuento>101.86</Descuento>
                </IDDetalleFactura>
                <IDDetalleFactura>
                    <DescripcionDetalle>iihE75YGLlhZQqPMXmI2DfR3ENST2aaY3OunpGqnWZxyVrgQAa0DEuagDPqIb7Y7lko6xpedkdi7i8HHoew</DescripcionDetalle>
                    <Cantidad>2</Cantidad>
                    <ImporteUnitario>26.2</ImporteUnitario>
                    <ImporteTotal>63.4</ImporteTotal>
                </IDDetalleFactura>
                <IDDetalleFactura>
                    <DescripcionDetalle>pbMngN2M85lXVWQgAFalPRgpj3mDB1p35WsopY6OF</DescripcionDetalle>
                    <Cantidad>1</Cantidad>
                    <ImporteUnitario>87.42</ImporteUnitario>
                    <ImporteTotal>82.51</ImporteTotal>
                    <Descuento>19.23</Descuento>
                </IDDetalleFactura>
                <IDDetalleFactura>
                    <DescripcionDetalle>xMdwvBWH5p5IXYYkh0P8JLVYUVOV4j8Uf7VJ3SPFAHErvUlxNufaiiOowZZ7BMU9RdbRqLeOfYAtIqCtbvVewN9UV5zKRCMENpMNBy0Xsdmt15Gv45KCzGf4JGmy4ISTNQ4B1j15</DescripcionDetalle>
                    <Cantidad>2</Cantidad>
                    <ImporteUnitario>79.38</ImporteUnitario>
                    <ImporteTotal>30.73</ImporteTotal>
                    <Descuento>133.36</Descuento>
                </IDDetalleFactura>
                <IDDetalleFactura>
                    <DescripcionDetalle>I3iUtCF8RGo0u0m0CQPaD3B9AaOuac7DD4ZqchwuOFxARjqUJ81atEFUFm1yU2qdgZypGWuC0IP0j0QnH6lUHPChXgXZZeiOEKiKRvRY6FX</DescripcionDetalle>
                    <Cantidad>2</Cantidad>
                    <ImporteUnitario>73.3</ImporteUnitario>
                    <ImporteTotal>118.85</ImporteTotal>
                    <Descuento>48.38</Descuento>
                </IDDetalleFactura>
                <IDDetalleFactura>
                    <DescripcionDetalle>PJ3zECSVCdFYZMmq20XP9ZBEW826e6svqPmy1O4E3OqEx03m57KHrMQLo0ESDE3n9pVM1HcrBzF7tAmPetHm9VaFSYnRIwzrZoLua1RKZ1If3</DescripcionDetalle>
                    <Cantidad>2</Cantidad>
                    <ImporteUnitario>79.18</ImporteUnitario>
                    <ImporteTotal>24.91</ImporteTotal>
                    <Descuento>137.77</Descuento>
                </IDDetalleFactura>
                <IDDetalleFactura>
                    <DescripcionDetalle>EVQ8SWFugWXEXOf91e97s1cp7CPRk8zrgRtEIors4nAOnBSPjTV8YWVUQbfIpS</DescripcionDetalle>
                    <Cantidad>1</Cantidad>
                    <ImporteUnitario>62.64</ImporteUnitario>
                    <ImporteTotal>75.79</ImporteTotal>
                </IDDetalleFactura>
                <IDDetalleFactura>
                    <DescripcionDetalle>7JCCMGfzyoAKqiAoABzKJScFNHmJl58p9xYs9hWKi2TqVcBjCcKZyIwhTFNjR3llVZ</DescripcionDetalle>
                    <Cantidad>1</Cantidad>
                    <ImporteUnitario>77.19</ImporteUnitario>
                    <ImporteTotal>32.69</ImporteTotal>
                    <Descuento>50.17</Descuento>
                </IDDetalleFactura>
                <IDDetalleFactura>
                    <DescripcionDetalle>ownU5jqyqwTrkRLRSl2tbbhMA</DescripcionDetalle>
                    <Cantidad>1</Cantidad>
                    <ImporteUnitario>5.53</ImporteUnitario>
                    <ImporteTotal>6.69</ImporteTotal>
                </IDDetalleFactura>
                <IDDetalleFactura>
                    <DescripcionDetalle>uYgNDPuNNe2x7JLUcm7hYpQX0Vt4PwEHGQlDa3JwIqz7jbLDHxpev52UGQ71hpr6OVQvE3qVMf315Vf8GuXYTGIqMhE8GNie581kLSF6eDW0HvTJYZ2asetDUQBBMFdlt0PeugYYyInB07Uo4k1mI8SxnO8PBGAlKhUquY8Wy4cElq0TBcIlehJz0VwASRf2TfVI3mP7476ezQ4nWvU5FAPFlWzxjgvokE6XrFeC8aCe</DescripcionDetalle>
                    <Cantidad>1</Cantidad>
                    <ImporteUnitario>39.78</ImporteUnitario>
                    <ImporteTotal>48.13</ImporteTotal>
                </IDDetalleFactura>
                <IDDetalleFactura>
                    <DescripcionDetalle>gvWEgoUe7q</DescripcionDetalle>
                    <Cantidad>1</Cantidad>
                    <ImporteUnitario>51.12</ImporteUnitario>
                    <ImporteTotal>56.91</ImporteTotal>
                    <Descuento>4.09</Descuento>
                </IDDetalleFactura>
                <IDDetalleFactura>
                    <DescripcionDetalle>9jRGZWpzywmP46G0Xm9fQqmcUkdiSPZQyI7ZaYhNgGFkaZVrPNP9QOnFg06cprHfkaXpK4PXW5vOtyA1k9jh25XKk8HD3sMcfn1UYbveiN2anKG8YSHPht8V8m9fkVwqX6ab5PGNyq6Stooei874zjDIDFGAHLji5q9SKo9tSw9Syv8tyG3eLr6rGuPbx8H52aSzM</DescripcionDetalle>
                    <Cantidad>1</Cantidad>
                    <ImporteUnitario>45.58</ImporteUnitario>
                    <ImporteTotal>39.71</ImporteTotal>
                    <Descuento>12.76</Descuento>
                </IDDetalleFactura>
                <IDDetalleFactura>
                    <DescripcionDetalle>FjrVz1pBgJAUVJaq5XMRvEGPL5k5suXRJZHeygYQPz0qS5n8MpiiB5myXAtkcDneCgGANqFx4tK7UfgaAW9iqYW1F737twVsehq4Qq6B0xb1dJjTWUg44Wz5NJky76qkRradcgJJehgxnwCBJS6i7KmpkzDsGoNk6LB4KxlAFSddOx5X2N2yakCK2gK1uUahT22xDm9zb1BUAstTPPbSzg37j8en7i1Ac71T</DescripcionDetalle>
                    <Cantidad>1</Cantidad>
                    <ImporteUnitario>46.25</ImporteUnitario>
                    <ImporteTotal>55.96</ImporteTotal>
                </IDDetalleFactura>
                <IDDetalleFactura>
                    <DescripcionDetalle>BVODfte9Hd9slbVCd6Wbw8OjHhlSwZYQfEvFVkeVnlF8nKjYhuv7ziVxKsAe1UPS2MdrbPtrbzIVUciWHfBtau2KN8tAccF5efxj6POk6RDoybKt1RKNbFvEVOl650kO57ErdJ7rhnoUM4UspbsuWgnTUoGYPviXtZ8Lf7AoHYrMAwChlVPQ9xp9d968w24ZfZeuLm1pqffV7tTLWprD5FJTjBg1wOWt4HhuhlfDXJ</DescripcionDetalle>
                    <Cantidad>1</Cantidad>
                    <ImporteUnitario>43.73</ImporteUnitario>
                    <ImporteTotal>52.91</ImporteTotal>
                </IDDetalleFactura>
                <IDDetalleFactura>
                    <DescripcionDetalle>z2ygq6KFdc59y1pIlUrS5q1LTylwokmvL53tnHuhWH2nSsSyEno66qHYYHjcZpX1MzWOon4C268q6F5tRgEqjDaRYKsRjUInFVIxnmAQqYTxHK87JLNW9LqCVGcNxcG05klmszpvFM7rjVvoJOwxWA9oRP94fS8HncobPa5fr6DAHn5YGlhDfDQIQYjEGgQ0D1JYqOLo00uTyfOK8yI0jMsiU9eb6i545k26noUxjolIez9eyYU9fTTD0r</DescripcionDetalle>
                    <Cantidad>2</Cantidad>
                    <ImporteUnitario>14.16</ImporteUnitario>
                    <ImporteTotal>30.15</ImporteTotal>
                    <Descuento>3.4</Descuento>
                </IDDetalleFactura>
                <IDDetalleFactura>
                    <DescripcionDetalle>dXrxdHnmgTGMvcDM8eS</DescripcionDetalle>
                    <Cantidad>1</Cantidad>
                    <ImporteUnitario>92.47</ImporteUnitario>
                    <ImporteTotal>111.89</ImporteTotal>
                </IDDetalleFactura>
                <IDDetalleFactura>
                    <DescripcionDetalle>jncFd3WxlQjy2G2K9z9kCN26fmg5x8rVEPRty0xzDFVwLj3xmm6OKmrw2HlnjhUdxnp5oWOYhBUVrhbQlKBJmUo59EjKTrm1uIo7H7PqEJnPZ7umkftmiFdyM9sqYyMPEoWNk6n85cyKbc1xkentl9iyFdCztagzuePVBpaOUeMHoKuHTbBuLcvHbMdk</DescripcionDetalle>
                    <Cantidad>2</Cantidad>
                    <ImporteUnitario>90.53</ImporteUnitario>
                    <ImporteTotal>219.08</ImporteTotal>
                </IDDetalleFactura>
                <IDDetalleFactura>
                    <DescripcionDetalle>nh5mPRkOmgBBhOnelzDDbUeM09ntuhhJCd3eRh8SBdrLnRvT35z10GZM45K34kxIVIWfqry1fp3HPCZcuDaS7vIs4fAD8McIpu1</DescripcionDetalle>
                    <Cantidad>2</Cantidad>
                    <ImporteUnitario>21.19</ImporteUnitario>
                    <ImporteTotal>16.93</ImporteTotal>
                    <Descuento>28.39</Descuento>
                </IDDetalleFactura>
                <IDDetalleFactura>
                    <DescripcionDetalle>sn3Q1gGkkqLgwRwqeVMvEegflC7oTWToKxhAclBloaQzT5wg6lfocnUHniV0KLFIV7DrOAlb4pONZW05</DescripcionDetalle>
                    <Cantidad>1</Cantidad>
                    <ImporteUnitario>47.14</ImporteUnitario>
                    <ImporteTotal>16.54</ImporteTotal>
                    <Descuento>33.47</Descuento>
                </IDDetalleFactura>
                <IDDetalleFactura>
                    <DescripcionDetalle>pUEy9JLFk5VOo</DescripcionDetalle>
                    <Cantidad>1</Cantidad>
                    <ImporteUnitario>15.51</ImporteUnitario>
                    <ImporteTotal>8.82</ImporteTotal>
                    <Descuento>8.22</Descuento>
                </IDDetalleFactura>
                <IDDetalleFactura>
                    <DescripcionDetalle>vdROEIcud2mFlehjf5tnGjPdNDyRL8D69FVJfO7gLSatNzLSs4TaTQlHQMYQ1tskcmZtvsUvzya7UJ</DescripcionDetalle>
                    <Cantidad>1</Cantidad>
                    <ImporteUnitario>31.23</ImporteUnitario>
                    <ImporteTotal>20.79</ImporteTotal>
                    <Descuento>14.05</Descuento>
                </IDDetalleFactura>
                <IDDetalleFactura>
                    <DescripcionDetalle>428FNKZYDIlmLOS5qp72w4WRCBbCHe9kXt0RhkbfF9l7DUbOz5PKJGWvPirWCrlrxIO3HASfzLIN6IUKAM4QZn0eK6B09VecuJEFSVrveunGjLiPHjVziQBWIQ0zEhrac9MWh7PvA7JdF7cwW7WfUsrOEV1RJa64g9baXhEfiK9nJlBVfoWGSwIsYXrxV0HAVyYBGD</DescripcionDetalle>
                    <Cantidad>1</Cantidad>
                    <ImporteUnitario>88.28</ImporteUnitario>
                    <ImporteTotal>106.82</ImporteTotal>
                </IDDetalleFactura>
                <IDDetalleFactura>
                    <DescripcionDetalle>NNMzxYMA7ZTXRuNyPARem4XgjU5vX34jZEmrSUQFq9ZiURh3WuNsaUh7JqAviJlazoZlfljGx8vqxENmJxX1sFtXINlJCFRgF9xoiHxM4ZMAwOIlVjqNmiaO9Y1FlnMdLwO6SX7P1iwpXtzn67EVuu6MC9SCPG92U0OosMFEh</DescripcionDetalle>
                    <Cantidad>2</Cantidad>
                    <ImporteUnitario>67.05</ImporteUnitario>
                    <ImporteTotal>38.94</ImporteTotal>
                    <Descuento>101.92</Descuento>
                </IDDetalleFactura>
                <IDDetalleFactura>
                    <DescripcionDetalle>skfJL5nAGZwEoLyg</DescripcionDetalle>
                    <Cantidad>1</Cantidad>
                    <ImporteUnitario>75.99</ImporteUnitario>
                    <ImporteTotal>91.95</ImporteTotal>
                </IDDetalleFactura>
                <IDDetalleFactura>
                    <DescripcionDetalle>B5CTJdSVaMd8iKZPiR</DescripcionDetalle>
                    <Cantidad>2</Cantidad>
                    <ImporteUnitario>72.63</ImporteUnitario>
                    <ImporteTotal>175.76</ImporteTotal>
                </IDDetalleFactura>
                <IDDetalleFactura>
                    <DescripcionDetalle>8CoshADEsp6GF2xpepYzn1nQ2xEUlWeaSn3X4PNNjTduWUrpwqe93F79L1T8Foydo6cYF4pTOus3JT4bF2hqSqX7ln8PTab9e8m34IkdKR431gO37QYVQWdQEhamO</DescripcionDetalle>
                    <Cantidad>2</Cantidad>
                    <ImporteUnitario>23.2</ImporteUnitario>
                    <ImporteTotal>56.14</ImporteTotal>
                </IDDetalleFactura>
                <IDDetalleFactura>
                    <DescripcionDetalle>k1B13cxl3l1GzLUEnr89nvSsLtj2gn2x4Vs1t5g6lODGmg3fgy61GznQSqn7Ao</DescripcionDetalle>
                    <Cantidad>1</Cantidad>
                    <ImporteUnitario>91.97</ImporteUnitario>
                    <ImporteTotal>32.27</ImporteTotal>
                    <Descuento>65.3</Descuento>
                </IDDetalleFactura>
                <IDDetalleFactura>
                    <DescripcionDetalle>3IjYTHUKfeNIv4YgnFFQwzrxm7qz8h2U3b7j15egxTEiMq3UCm10yWOYLPk7oXvBBARZPBzR8U0RqKDjIDauaPk</DescripcionDetalle>
                    <Cantidad>1</Cantidad>
                    <ImporteUnitario>46.67</ImporteUnitario>
                    <ImporteTotal>56.47</ImporteTotal>
                </IDDetalleFactura>
                <IDDetalleFactura>
                    <DescripcionDetalle>XeLkAXydxmcRa0vXR13QqrO2gD1WuiPSMq8JwXNZ7eB4Ev3yeSztDJFAfBk8i3OTBENKEWNFifcPXRp9THR4nxjSOXWM3s2wnqoZItTp9it6f5HqyB3ZalT5zJpLRbfZmE1OGQHGIqjzLPlhFDd5cpXtDAeZu2gdR6XCfGiFZSykZwAdfwlxItNkToItDlZ8ZbNmU3GVN9QPwa4Jf7ewPIjdRFdBroOLcGQp7jVW1qjzL32</DescripcionDetalle>
                    <Cantidad>1</Cantidad>
                    <ImporteUnitario>56.28</ImporteUnitario>
                    <ImporteTotal>68.1</ImporteTotal>
                </IDDetalleFactura>
                <IDDetalleFactura>
                    <DescripcionDetalle>Kfq2iczDsP3u4NhpI8kbahwuNHqCtiD65UrdBBfq2ikNI6BCRIz4I85drbyeWjPi5cLXX061UDNVE09vyGewDzoLhCPmoNEX9zB3LnxDiHB5bO57PwQeZVPiWzEmnY97s3tr1mLkeov9TZGJNH7VwIpb0C</DescripcionDetalle>
                    <Cantidad>2</Cantidad>
                    <ImporteUnitario>34.86</ImporteUnitario>
                    <ImporteTotal>84.36</ImporteTotal>
                </IDDetalleFactura>
                <IDDetalleFactura>
                    <DescripcionDetalle>vxIJzTkLO40cl7COAqPaUQSRTypDB36DwXFswUAdYEl59dQbThpbM67t7VazfcYiDPNP3d9CpOiRlGFDIYnMcNVTsx8LnVklxfIdNVj4Mf1GpZ8FTvU6YUp5Hzfl6mQ4iu3USlvGA26jL88T2ahRHcL8Wfz5ed9VOS5sStVZwtmMVHyF3MCWd9Dm7eF3jtFuo2iGKRn</DescripcionDetalle>
                    <Cantidad>2</Cantidad>
                    <ImporteUnitario>46.34</ImporteUnitario>
                    <ImporteTotal>112.14</ImporteTotal>
                </IDDetalleFactura>
                <IDDetalleFactura>
                    <DescripcionDetalle>em5dpLXw04YmkK1dWs6DiP20dlnZObJJOUVYy1KDAu2z3aXZPr8eWiYdOnQJcMfUBQmrVZQh4PSYOf5vyHdsgMU3E0vOaQdslXkPph8A3OrWlwLahIcWl7uv2Itg1ONknCngx7zZ393gIIt3H3RpPICtUQZSMamGZoJ96qTPy13xvY1cX0Gy9PNpPJXXU4ywAENYUPmZSK17fl1xt8uL8nosIrX2ZgaOSbdpFJBgpnYwRHst</DescripcionDetalle>
                    <Cantidad>2</Cantidad>
                    <ImporteUnitario>32.82</ImporteUnitario>
                    <ImporteTotal>59.57</ImporteTotal>
                    <Descuento>16.41</Descuento>
                </IDDetalleFactura>
                <IDDetalleFactura>
                    <DescripcionDetalle>pXlJbIZXJKqtV65paabs8sfxaI3fKzdnoBZe0jhjFVgguFPLzfjHAlRco6HaKPBgN5mrXuKqQfFkcOZ74A3jhaHXLQ3EeHcYXh</DescripcionDetalle>
                    <Cantidad>1</Cantidad>
                    <ImporteUnitario>17.65</ImporteUnitario>
                    <ImporteTotal>19.65</ImporteTotal>
                    <Descuento>1.41</Descuento>
                </IDDetalleFactura>
                <IDDetalleFactura>
                    <DescripcionDetalle>Rzg5UP30IOrsGrH7XWjwivy3rDPdYL65oik53Wlr6t3RWY</DescripcionDetalle>
                    <Cantidad>2</Cantidad>
                    <ImporteUnitario>72.39</ImporteUnitario>
                    <ImporteTotal>57.81</ImporteTotal>
                    <Descuento>97</Descuento>
                </IDDetalleFactura>
                <IDDetalleFactura>
                    <DescripcionDetalle>mQExRtLs1bs8RTXrnf1UMMWMuMvbylBiJzCETxfsDtDEyY6JpFevxDtwJBT48pjwyuVa7Xvo16ItiuGTVaLrhfUd119SjgEs3v6et4OSf5cTSEf8opUnmo8DYFB2gkrnCMoYj2lFIRcW2IXwJx5hUyFUv2mPLS54KnFXziW8nRIHldHOKsyix2tT5isAhXt9sBgswA4YAo4KEWW6NvLx2E9Pdy8uAZqaeyxMGaULUAn9FLqm4co0cgF4vy</DescripcionDetalle>
                    <Cantidad>1</Cantidad>
                    <ImporteUnitario>7.81</ImporteUnitario>
                    <ImporteTotal>9.45</ImporteTotal>
                </IDDetalleFactura>
                <IDDetalleFactura>
                    <DescripcionDetalle>OSp3EfVnyIM4W5JY2ONmynai2opCvLagzx886BqfCQdlzmBWyFkYUz2eqLXLIOpO4F4AFKkQ9x8fm6lKQw4yD9uIfbQfs0HjLXYUEndQoaX3unAzbBBC8GWFRyp5An1e</DescripcionDetalle>
                    <Cantidad>2</Cantidad>
                    <ImporteUnitario>16.46</ImporteUnitario>
                    <ImporteTotal>-0.4</ImporteTotal>
                    <Descuento>33.25</Descuento>
                </IDDetalleFactura>
                <IDDetalleFactura>
                    <DescripcionDetalle>koqMU2PxWPQlOU6Ebi7wGXCA9Kj4BqZGiW5FcgZMdeC6dTVa3AsYA3JULX8bgM0XVC1yS6JWKOyn15ybOqalaMTMmxTTh9Yb5ASA6xdJgF46laz3p1Mg4bRRft75AcvBYm6q6QFDmeXYhl8ATmc2HUharz14NEQsDs16wJvO29JUEJZPqdd52Ji2cbDUOMmHVTVuuws45aUWKxLl82GxjKvQau4xIZ</DescripcionDetalle>
                    <Cantidad>1</Cantidad>
                    <ImporteUnitario>74.46</ImporteUnitario>
                    <ImporteTotal>90.1</ImporteTotal>
                </IDDetalleFactura>
                <IDDetalleFactura>
                    <DescripcionDetalle>EC7bqBpEvp2hmef3Ma2VE98fggQtICeMviblQGnuQ43YM8222BS0X</DescripcionDetalle>
                    <Cantidad>1</Cantidad>
                    <ImporteUnitario>79.92</ImporteUnitario>
                    <ImporteTotal>50.29</ImporteTotal>
                    <Descuento>38.36</Descuento>
                </IDDetalleFactura>
                <IDDetalleFactura>
                    <DescripcionDetalle>cgmuM6MbWUghowP3Li6RZLClIrfJbQqLRgg6WkU9L8MPHU7EqRgZ9SthWubRiQf4pKpOmyLsk4DGB4hTuo8hMjTpv5WGneWdbVO5ddhhpAGuFapv9uBlMwv5a0W7p8v7MTreUCeaDn6H12vDSJDuKuY0P1AtUGcnb9eafVsRapJDL0TgFNH6INnFYzzVPOf9pVv6ydTJMSrPobkdqRm8lqYTLn7sJJChh</DescripcionDetalle>
                    <Cantidad>2</Cantidad>
                    <ImporteUnitario>3.67</ImporteUnitario>
                    <ImporteTotal>8.88</ImporteTotal>
                </IDDetalleFactura>
                <IDDetalleFactura>
                    <DescripcionDetalle>gMfUfOMLCbvLTmB40PVSheqomlhHNv2RLKIj9i5pGtLM36rH9Rmyfx7uUwhSMWGTYVI75oXIa5aZv7SoEVS3KLSRuiBlKJeJPURzEpy6D0DlQGBV5akNAKS9cUat4fJTZL7uH86PEG3Vau1Jz2XLQ13k2X4pPuxlGtf1kDq3TI3QKif</DescripcionDetalle>
                    <Cantidad>1</Cantidad>
                    <ImporteUnitario>84.84</ImporteUnitario>
                    <ImporteTotal>67.75</ImporteTotal>
                    <Descuento>28.85</Descuento>
                </IDDetalleFactura>
                <IDDetalleFactura>
                    <DescripcionDetalle>4ymLAFRTOqSJAPB</DescripcionDetalle>
                    <Cantidad>2</Cantidad>
                    <ImporteUnitario>34.85</ImporteUnitario>
                    <ImporteTotal>78.43</ImporteTotal>
                    <Descuento>4.88</Descuento>
                </IDDetalleFactura>
                <IDDetalleFactura>
                    <DescripcionDetalle>L7phxup0Q06w6cs6ZpWHnhxw0PMYL2ES3lu8WUKcnifIfwl2sn64ecEdoSnEMOcdviJb3uASffqWm6d68ChUO3yDXT9pKfmo388pWwQTsvyzDG0NCW3se3oPXQPowZVgdYewKNAdEjQPayqIhbD6jCuLmYTHvPCJVBlDfkcOxR2aq4Fz0K3XcEpw8jXT8denLaqiW3kBYW2cXxQ2ZPf</DescripcionDetalle>
                    <Cantidad>2</Cantidad>
                    <ImporteUnitario>7.88</ImporteUnitario>
                    <ImporteTotal>5.53</ImporteTotal>
                    <Descuento>11.19</Descuento>
                </IDDetalleFactura>
                <IDDetalleFactura>
                    <DescripcionDetalle>WT2IYAvAojN4uFmTPEnG0coEoxqGUrcDzrBIgVmeU54ZUw1eoPnv4IMknvZjmLQbBH0CfMgiqZS4D0oginTiGggjUETbl8fUKg1M0VZNnUA6hsSbPysIVC8IfEcxmONx62jPB54LRXEEjfGD9Qj</DescripcionDetalle>
                    <Cantidad>1</Cantidad>
                    <ImporteUnitario>81.53</ImporteUnitario>
                    <ImporteTotal>43.4</ImporteTotal>
                    <Descuento>45.66</Descuento>
                </IDDetalleFactura>
                <IDDetalleFactura>
                    <DescripcionDetalle>8gUA5oPY6wDHDCOBEhZ3BgoClTMYQIHmZ5ZAdLVLOXuZnxElOggsGDchMs72dTaq3ycKfN0FE8WPU2Q3MQSJI4LpHUvO2ypiwie72aUz3tvFX9eeAPf1LBnMxt4gk6NOXMwhsV1DUfpr2G32SVIIbTLGq2mP8NGoN2wJl9e7JuI9LVW7joKKwo8C6fKvON3fF5AMVdT7kkxqgymeg3Q2x9toD2fcrk18WhZ6hHkCuIhT</DescripcionDetalle>
                    <Cantidad>2</Cantidad>
                    <ImporteUnitario>23.09</ImporteUnitario>
                    <ImporteTotal>55.88</ImporteTotal>
                    <Descuento>0</Descuento>
                </IDDetalleFactura>
                <IDDetalleFactura>
                    <DescripcionDetalle>TJefsWuej3CXm2luMuDilUEE9iapLB6BV6pwNfFQ2uDzepksm054p4gVwiDoEpIR1si2GxcctyMXynqu3tEVF6ZZY18BlID9sWho0bTVSUJyipLjGpVFfA7ReJMygEuLUH7ZJZRiJAVbuzE2kMpYWawTooB7J3aYcdJXBNUXHWPpo3ZNd4YkjzCSm9iWP7WyyCRHJ6HrOWbwQon9XeWEHPp4HUyNh05MOJWM4ksE</DescripcionDetalle>
                    <Cantidad>2</Cantidad>
                    <ImporteUnitario>35.1</ImporteUnitario>
                    <ImporteTotal>84.94</ImporteTotal>
                </IDDetalleFactura>
                <IDDetalleFactura>
                    <DescripcionDetalle>MUjcmoKkvbA3ftWKOwEDEGG8DmXABM2LelDQTrGJfDF2ovwe4QyiL20ismvMi2JIjqMVzW2vKBCUeP1rXo2q8tr8gYcw6yyDLALSj9LzaHIYtfZ60W</DescripcionDetalle>
                    <Cantidad>1</Cantidad>
                    <ImporteUnitario>20.33</ImporteUnitario>
                    <ImporteTotal>24.6</ImporteTotal>
                </IDDetalleFactura>
                <IDDetalleFactura>
                    <DescripcionDetalle>l18YeFoETWZUa0Sp5gtftUb4YX8VhklVAWRAkYKIpEpkVSuhT9nrEGzKyRN7MjDCQnjmLE2cb6Frj4GGVQisPlh8UMHPTEb3EAmVzYVnIV5Q37mvwOwBtLm1W9kYhqgiw1002K2Crx9FJQ3oqx1IfHA8</DescripcionDetalle>
                    <Cantidad>1</Cantidad>
                    <ImporteUnitario>92.76</ImporteUnitario>
                    <ImporteTotal>13.47</ImporteTotal>
                    <Descuento>81.63</Descuento>
                </IDDetalleFactura>
            </DetallesFactura>
            <ImporteTotalFactura>4788.35</ImporteTotalFactura>
            <FechaOperacion>18-11-2012</FechaOperacion>
            <RetencionSoportada>35309.29</RetencionSoportada>
            <BaseImponibleACoste>37608.67</BaseImponibleACoste>
            <Claves>
                <IDClave>
                    <ClaveRegimenIvaOpTrascendencia>53</ClaveRegimenIvaOpTrascendencia>
                </IDClave>
            </Claves>
        </DatosFactura>
        <TipoDesglose>
            <DesgloseTipoOperacion>
                <PrestacionServicios>
                    <Sujeta>
                        <Exenta>
                            <DetalleExenta>
                                <CausaExencion>E4</CausaExencion>
                                <BaseImponible>51</BaseImponible>
                            </DetalleExenta>
                            <DetalleExenta>
                                <CausaExencion>E1</CausaExencion>
                                <BaseImponible>26.98</BaseImponible>
                            </DetalleExenta>
                            <DetalleExenta>
                                <CausaExencion>E6</CausaExencion>
                                <BaseImponible>21.24</BaseImponible>
                            </DetalleExenta>
                            <DetalleExenta>
                                <CausaExencion>E5</CausaExencion>
                                <BaseImponible>91.4</BaseImponible>
                            </DetalleExenta>
                            <DetalleExenta>
                                <CausaExencion>E3</CausaExencion>
                                <BaseImponible>84.94</BaseImponible>
                            </DetalleExenta>
                        </Exenta>
                        <NoExenta>
                            <DetalleNoExenta>
                                <TipoNoExenta>S1</TipoNoExenta>
                                <DesgloseIVA>
                                    <DetalleIVA>
                                        <BaseImponible>486.80</BaseImponible>
                                        <TipoImpositivo>21</TipoImpositivo>
                                        <CuotaImpuesto>102.23</CuotaImpuesto>
                                        <TipoRecargoEquivalencia>4.56</TipoRecargoEquivalencia>
                                    </DetalleIVA>
                                </DesgloseIVA>
                            </DetalleNoExenta>
                        </NoExenta>
                    </Sujeta>
                    <NoSujeta>
                        <DetalleNoSujeta>
                            <Causa>OT</Causa>
                            <Importe>18824.56</Importe>
                        </DetalleNoSujeta>
                        <DetalleNoSujeta>
                            <Causa>RL</Causa>
                            <Importe>10330.76</Importe>
                        </DetalleNoSujeta>
                    </NoSujeta>
                </PrestacionServicios>
                <Entrega>
                    <Sujeta>
                        <Exenta>
                            <DetalleExenta>
                                <CausaExencion>E4</CausaExencion>
                                <BaseImponible>24.18</BaseImponible>
                            </DetalleExenta>
                            <DetalleExenta>
                                <CausaExencion>E3</CausaExencion>
                                <BaseImponible>74.6</BaseImponible>
                            </DetalleExenta>
                            <DetalleExenta>
                                <CausaExencion>E1</CausaExencion>
                                <BaseImponible>162.21</BaseImponible>
                            </DetalleExenta>
                            <DetalleExenta>
                                <CausaExencion>E2</CausaExencion>
                                <BaseImponible>203.1</BaseImponible>
                            </DetalleExenta>
                            <DetalleExenta>
                                <CausaExencion>E6</CausaExencion>
                                <BaseImponible>71.98</BaseImponible>
                            </DetalleExenta>
                        </Exenta>
                        <NoExenta>
                            <DetalleNoExenta>
                                <TipoNoExenta>S1</TipoNoExenta>
                                <DesgloseIVA>
                                    <DetalleIVA>
                                        <BaseImponible>1318.62</BaseImponible>
                                        <TipoImpositivo>21</TipoImpositivo>
                                        <CuotaImpuesto>276.91</CuotaImpuesto>
                                        <TipoRecargoEquivalencia>57.98</TipoRecargoEquivalencia>
                                        <CuotaRecargoEquivalencia>84881.2</CuotaRecargoEquivalencia>
                                        <OperacionEnRecargoDeEquivalenciaORegimenSimplificado>N</OperacionEnRecargoDeEquivalenciaORegimenSimplificado>
                                    </DetalleIVA>
                                </DesgloseIVA>
                            </DetalleNoExenta>
                        </NoExenta>
                    </Sujeta>
                    <NoSujeta>
                        <DetalleNoSujeta>
                            <Causa>OT</Causa>
                            <Importe>16667.03</Importe>
                        </DetalleNoSujeta>
                        <DetalleNoSujeta>
                            <Causa>RL</Causa>
                            <Importe>26245.95</Importe>
                        </DetalleNoSujeta>
                    </NoSujeta>
                </Entrega>
            </DesgloseTipoOperacion>
        </TipoDesglose>
    </Factura>
    <HuellaTBAI Id="_10455">
        <Software>
            <LicenciaTBAI>SkYmHhywM</LicenciaTBAI>
            <EntidadDesarrolladora>
                <NIF>65500346A</NIF>
            </EntidadDesarrolladora>
            <Nombre>FFD06CBAwTmnww5mZxXcCvzEln4qswC8KeMW</Nombre>
            <Version>yt2f7QWFpfQI0fnX</Version>
        </Software>
    </HuellaTBAI>
<Signature xmlns="http://www.w3.org/2000/09/xmldsig#"><SignedInfo><CanonicalizationMethod Algorithm="http://www.w3.org/2001/10/xml-exc-c14n#"/><SignatureMethod Algorithm="http://www.w3.org/2000/09/xmldsig#rsa-sha1"/><Reference URI="#_10452"><Transforms><Transform Algorithm="http://www.w3.org/2001/10/xml-exc-c14n#"/></Transforms><DigestMethod Algorithm="http://www.w3.org/2000/09/xmldsig#sha1"/><DigestValue>Cw/q1RIQ1dpRFBPtIu1Et8mBMHI=</DigestValue></Reference><Reference URI="#_10453"><Transforms><Transform Algorithm="http://www.w3.org/2001/10/xml-exc-c14n#"/></Transforms><DigestMethod Algorithm="http://www.w3.org/2000/09/xmldsig#sha1"/><DigestValue>L5r/QRWv3FLz5NNxlwdn9NyCpNo=</DigestValue></Reference><Reference URI="#_10454"><Transforms><Transform Algorithm="http://www.w3.org/2001/10/xml-exc-c14n#"/></Transforms><DigestMethod Algorithm="http://www.w3.org/2000/09/xmldsig#sha1"/><DigestValue>J8MFVpYmwo9uxkeCiloeX+TszNw=</DigestValue></Reference><Reference URI="#_10455"><Transforms><Transform Algorithm="http://www.w3.org/2001/10/xml-exc-c14n#"/></Transforms><DigestMethod Algorithm="http://www.w3.org/2000/09/xmldsig#sha1"/><DigestValue>nuPQsRcpnpRRnx0FKca/EKya364=</DigestValue></Reference></SignedInfo><SignatureValue>zvo7CpDHS9PJhDApE9JP/4+4iGb7HUJsSqduHdvnNFlKdtCSHI0zzOizaOTej5UEVJNni9uhmy+hLyoyeFd7iOafUKjgTmWBefXpy2RTQzlk+kBQ3ninf3InJ+apk2Rt9FTEysGMtKw2BGLRS9wKbq8dOo0D4e2QN26wEKnL/hG1S6NNeWhBCxW1MZTH/n/qUu341+gTIUg9J4xlafEt97l8xCexaoVYdHItXhbXOdIGwpcuASu6qvfznCNwfy+l9UNd1tGgF2Z0py8PoUX6r5i8eJ1VCu9AJ2we8fzwk6sd5593yGnrhrWeV6d6E7se+QNXAxOv/Gp7uchBXaZpvw==</SignatureValue></Signature></T:TicketBai>